<?xml version="1.0" encoding="UTF-8"?>
<spirit:component xmlns:xilinx="http://www.xilinx.com" xmlns:spirit="http://www.spiritconsortium.org/XMLSchema/SPIRIT/1685-2009" xmlns:xsi="http://www.w3.org/2001/XMLSchema-instance">
  <spirit:vendor>xilinx.com</spirit:vendor>
  <spirit:library>customized_ip</spirit:library>
  <spirit:name>bd_3d9a_shell_cmc_subsystem_0</spirit:name>
  <spirit:version>1.0</spirit:version>
  <spirit:busInterfaces>
    <spirit:busInterface>
      <spirit:name>CLK.aclk_ctrl</spirit:name>
      <spirit:busType spirit:vendor="xilinx.com" spirit:library="signal" spirit:name="clock" spirit:version="1.0"/>
      <spirit:abstractionType spirit:vendor="xilinx.com" spirit:library="signal" spirit:name="clock_rtl" spirit:version="1.0"/>
      <spirit:slave/>
      <spirit:portMaps>
        <spirit:portMap>
          <spirit:logicalPort>
            <spirit:name>CLK</spirit:name>
          </spirit:logicalPort>
          <spirit:physicalPort>
            <spirit:name>aclk_ctrl</spirit:name>
          </spirit:physicalPort>
        </spirit:portMap>
      </spirit:portMaps>
      <spirit:parameters>
        <spirit:parameter>
          <spirit:name>FREQ_HZ</spirit:name>
          <spirit:value spirit:format="long" spirit:resolve="generated" spirit:id="BUSIFPARAM_VALUE.CLK.ACLK_CTRL.FREQ_HZ">50000000</spirit:value>
          <spirit:vendorExtensions>
            <xilinx:parameterInfo>
              <xilinx:parameterUsage>none</xilinx:parameterUsage>
            </xilinx:parameterInfo>
          </spirit:vendorExtensions>
        </spirit:parameter>
        <spirit:parameter>
          <spirit:name>PHASE</spirit:name>
          <spirit:value spirit:format="float" spirit:resolve="generated" spirit:id="BUSIFPARAM_VALUE.CLK.ACLK_CTRL.PHASE">0.0</spirit:value>
          <spirit:vendorExtensions>
            <xilinx:parameterInfo>
              <xilinx:parameterUsage>none</xilinx:parameterUsage>
            </xilinx:parameterInfo>
          </spirit:vendorExtensions>
        </spirit:parameter>
        <spirit:parameter>
          <spirit:name>CLK_DOMAIN</spirit:name>
          <spirit:value spirit:resolve="generated" spirit:id="BUSIFPARAM_VALUE.CLK.ACLK_CTRL.CLK_DOMAIN">PCIe_Bridge_ICAP_complex_clk_wiz_0_0_clk_out_125M</spirit:value>
          <spirit:vendorExtensions>
            <xilinx:parameterInfo>
              <xilinx:parameterUsage>none</xilinx:parameterUsage>
            </xilinx:parameterInfo>
          </spirit:vendorExtensions>
        </spirit:parameter>
        <spirit:parameter>
          <spirit:name>ASSOCIATED_BUSIF</spirit:name>
          <spirit:value spirit:resolve="generated" spirit:id="BUSIFPARAM_VALUE.CLK.ACLK_CTRL.ASSOCIATED_BUSIF">s_axi_ctrl_mgmt</spirit:value>
          <spirit:vendorExtensions>
            <xilinx:parameterInfo>
              <xilinx:parameterUsage>none</xilinx:parameterUsage>
            </xilinx:parameterInfo>
          </spirit:vendorExtensions>
        </spirit:parameter>
        <spirit:parameter>
          <spirit:name>ASSOCIATED_RESET</spirit:name>
          <spirit:value spirit:resolve="generated" spirit:id="BUSIFPARAM_VALUE.CLK.ACLK_CTRL.ASSOCIATED_RESET">aresetn_ctrl</spirit:value>
          <spirit:vendorExtensions>
            <xilinx:parameterInfo>
              <xilinx:parameterUsage>none</xilinx:parameterUsage>
            </xilinx:parameterInfo>
          </spirit:vendorExtensions>
        </spirit:parameter>
        <spirit:parameter>
          <spirit:name>INSERT_VIP</spirit:name>
          <spirit:value spirit:format="long" spirit:resolve="user" spirit:id="BUSIFPARAM_VALUE.CLK.ACLK_CTRL.INSERT_VIP">0</spirit:value>
          <spirit:vendorExtensions>
            <xilinx:parameterInfo>
              <xilinx:parameterUsage>simulation.rtl</xilinx:parameterUsage>
            </xilinx:parameterInfo>
          </spirit:vendorExtensions>
        </spirit:parameter>
        <spirit:parameter>
          <spirit:name>ASSOCIATED_CLKEN</spirit:name>
          <spirit:value spirit:resolve="generated" spirit:id="BUSIFPARAM_VALUE.CLK.ACLK_CTRL.ASSOCIATED_CLKEN">CE</spirit:value>
          <spirit:vendorExtensions>
            <xilinx:parameterInfo>
              <xilinx:parameterUsage>none</xilinx:parameterUsage>
            </xilinx:parameterInfo>
          </spirit:vendorExtensions>
        </spirit:parameter>
      </spirit:parameters>
    </spirit:busInterface>
    <spirit:busInterface>
      <spirit:name>RST.aresetn_ctrl</spirit:name>
      <spirit:busType spirit:vendor="xilinx.com" spirit:library="signal" spirit:name="reset" spirit:version="1.0"/>
      <spirit:abstractionType spirit:vendor="xilinx.com" spirit:library="signal" spirit:name="reset_rtl" spirit:version="1.0"/>
      <spirit:slave/>
      <spirit:portMaps>
        <spirit:portMap>
          <spirit:logicalPort>
            <spirit:name>RST</spirit:name>
          </spirit:logicalPort>
          <spirit:physicalPort>
            <spirit:name>aresetn_ctrl</spirit:name>
          </spirit:physicalPort>
        </spirit:portMap>
      </spirit:portMaps>
      <spirit:parameters>
        <spirit:parameter>
          <spirit:name>POLARITY</spirit:name>
          <spirit:value spirit:resolve="generated" spirit:id="BUSIFPARAM_VALUE.RST.ARESETN_CTRL.POLARITY">ACTIVE_LOW</spirit:value>
          <spirit:vendorExtensions>
            <xilinx:parameterInfo>
              <xilinx:parameterUsage>none</xilinx:parameterUsage>
            </xilinx:parameterInfo>
          </spirit:vendorExtensions>
        </spirit:parameter>
        <spirit:parameter>
          <spirit:name>INSERT_VIP</spirit:name>
          <spirit:value spirit:format="long" spirit:resolve="user" spirit:id="BUSIFPARAM_VALUE.RST.ARESETN_CTRL.INSERT_VIP">0</spirit:value>
          <spirit:vendorExtensions>
            <xilinx:parameterInfo>
              <xilinx:parameterUsage>simulation.rtl</xilinx:parameterUsage>
            </xilinx:parameterInfo>
          </spirit:vendorExtensions>
        </spirit:parameter>
      </spirit:parameters>
    </spirit:busInterface>
    <spirit:busInterface>
      <spirit:name>RST.mdm_debug_sys_rst</spirit:name>
      <spirit:busType spirit:vendor="xilinx.com" spirit:library="signal" spirit:name="reset" spirit:version="1.0"/>
      <spirit:abstractionType spirit:vendor="xilinx.com" spirit:library="signal" spirit:name="reset_rtl" spirit:version="1.0"/>
      <spirit:slave/>
      <spirit:portMaps>
        <spirit:portMap>
          <spirit:logicalPort>
            <spirit:name>RST</spirit:name>
          </spirit:logicalPort>
          <spirit:physicalPort>
            <spirit:name>mdm_debug_sys_rst</spirit:name>
          </spirit:physicalPort>
        </spirit:portMap>
      </spirit:portMaps>
      <spirit:parameters>
        <spirit:parameter>
          <spirit:name>POLARITY</spirit:name>
          <spirit:value spirit:resolve="generated" spirit:id="BUSIFPARAM_VALUE.RST.MDM_DEBUG_SYS_RST.POLARITY">ACTIVE_HIGH</spirit:value>
          <spirit:vendorExtensions>
            <xilinx:parameterInfo>
              <xilinx:parameterUsage>none</xilinx:parameterUsage>
            </xilinx:parameterInfo>
          </spirit:vendorExtensions>
        </spirit:parameter>
        <spirit:parameter>
          <spirit:name>INSERT_VIP</spirit:name>
          <spirit:value spirit:format="long" spirit:resolve="user" spirit:id="BUSIFPARAM_VALUE.RST.MDM_DEBUG_SYS_RST.INSERT_VIP">0</spirit:value>
          <spirit:vendorExtensions>
            <xilinx:parameterInfo>
              <xilinx:parameterUsage>simulation.rtl</xilinx:parameterUsage>
            </xilinx:parameterInfo>
          </spirit:vendorExtensions>
        </spirit:parameter>
      </spirit:parameters>
    </spirit:busInterface>
    <spirit:busInterface>
      <spirit:name>INTR.interrupt_host</spirit:name>
      <spirit:busType spirit:vendor="xilinx.com" spirit:library="signal" spirit:name="interrupt" spirit:version="1.0"/>
      <spirit:abstractionType spirit:vendor="xilinx.com" spirit:library="signal" spirit:name="interrupt_rtl" spirit:version="1.0"/>
      <spirit:master/>
      <spirit:portMaps>
        <spirit:portMap>
          <spirit:logicalPort>
            <spirit:name>INTERRUPT</spirit:name>
          </spirit:logicalPort>
          <spirit:physicalPort>
            <spirit:name>interrupt_host</spirit:name>
          </spirit:physicalPort>
        </spirit:portMap>
      </spirit:portMaps>
      <spirit:parameters>
        <spirit:parameter>
          <spirit:name>SENSITIVITY</spirit:name>
          <spirit:value spirit:resolve="generated" spirit:id="BUSIFPARAM_VALUE.INTR.INTERRUPT_HOST.SENSITIVITY">LEVEL_HIGH</spirit:value>
          <spirit:vendorExtensions>
            <xilinx:parameterInfo>
              <xilinx:parameterUsage>none</xilinx:parameterUsage>
            </xilinx:parameterInfo>
          </spirit:vendorExtensions>
        </spirit:parameter>
        <spirit:parameter>
          <spirit:name>PortWidth</spirit:name>
          <spirit:value spirit:format="long" spirit:resolve="generated" spirit:id="BUSIFPARAM_VALUE.INTR.INTERRUPT_HOST.PortWidth">1</spirit:value>
          <spirit:vendorExtensions>
            <xilinx:parameterInfo>
              <xilinx:parameterUsage>none</xilinx:parameterUsage>
            </xilinx:parameterInfo>
          </spirit:vendorExtensions>
        </spirit:parameter>
      </spirit:parameters>
    </spirit:busInterface>
    <spirit:busInterface>
      <spirit:name>s_axi_ctrl_mgmt</spirit:name>
      <spirit:busType spirit:vendor="xilinx.com" spirit:library="interface" spirit:name="aximm" spirit:version="1.0"/>
      <spirit:abstractionType spirit:vendor="xilinx.com" spirit:library="interface" spirit:name="aximm_rtl" spirit:version="1.0"/>
      <spirit:slave>
        <spirit:memoryMapRef spirit:memoryMapRef="s_axi_ctrl_mgmt"/>
      </spirit:slave>
      <spirit:portMaps>
        <spirit:portMap>
          <spirit:logicalPort>
            <spirit:name>AWADDR</spirit:name>
          </spirit:logicalPort>
          <spirit:physicalPort>
            <spirit:name>s_axi_ctrl_mgmt_awaddr</spirit:name>
          </spirit:physicalPort>
        </spirit:portMap>
        <spirit:portMap>
          <spirit:logicalPort>
            <spirit:name>AWPROT</spirit:name>
          </spirit:logicalPort>
          <spirit:physicalPort>
            <spirit:name>s_axi_ctrl_mgmt_awprot</spirit:name>
          </spirit:physicalPort>
        </spirit:portMap>
        <spirit:portMap>
          <spirit:logicalPort>
            <spirit:name>AWVALID</spirit:name>
          </spirit:logicalPort>
          <spirit:physicalPort>
            <spirit:name>s_axi_ctrl_mgmt_awvalid</spirit:name>
          </spirit:physicalPort>
        </spirit:portMap>
        <spirit:portMap>
          <spirit:logicalPort>
            <spirit:name>AWREADY</spirit:name>
          </spirit:logicalPort>
          <spirit:physicalPort>
            <spirit:name>s_axi_ctrl_mgmt_awready</spirit:name>
          </spirit:physicalPort>
        </spirit:portMap>
        <spirit:portMap>
          <spirit:logicalPort>
            <spirit:name>WDATA</spirit:name>
          </spirit:logicalPort>
          <spirit:physicalPort>
            <spirit:name>s_axi_ctrl_mgmt_wdata</spirit:name>
          </spirit:physicalPort>
        </spirit:portMap>
        <spirit:portMap>
          <spirit:logicalPort>
            <spirit:name>WSTRB</spirit:name>
          </spirit:logicalPort>
          <spirit:physicalPort>
            <spirit:name>s_axi_ctrl_mgmt_wstrb</spirit:name>
          </spirit:physicalPort>
        </spirit:portMap>
        <spirit:portMap>
          <spirit:logicalPort>
            <spirit:name>WVALID</spirit:name>
          </spirit:logicalPort>
          <spirit:physicalPort>
            <spirit:name>s_axi_ctrl_mgmt_wvalid</spirit:name>
          </spirit:physicalPort>
        </spirit:portMap>
        <spirit:portMap>
          <spirit:logicalPort>
            <spirit:name>WREADY</spirit:name>
          </spirit:logicalPort>
          <spirit:physicalPort>
            <spirit:name>s_axi_ctrl_mgmt_wready</spirit:name>
          </spirit:physicalPort>
        </spirit:portMap>
        <spirit:portMap>
          <spirit:logicalPort>
            <spirit:name>BRESP</spirit:name>
          </spirit:logicalPort>
          <spirit:physicalPort>
            <spirit:name>s_axi_ctrl_mgmt_bresp</spirit:name>
          </spirit:physicalPort>
        </spirit:portMap>
        <spirit:portMap>
          <spirit:logicalPort>
            <spirit:name>BVALID</spirit:name>
          </spirit:logicalPort>
          <spirit:physicalPort>
            <spirit:name>s_axi_ctrl_mgmt_bvalid</spirit:name>
          </spirit:physicalPort>
        </spirit:portMap>
        <spirit:portMap>
          <spirit:logicalPort>
            <spirit:name>BREADY</spirit:name>
          </spirit:logicalPort>
          <spirit:physicalPort>
            <spirit:name>s_axi_ctrl_mgmt_bready</spirit:name>
          </spirit:physicalPort>
        </spirit:portMap>
        <spirit:portMap>
          <spirit:logicalPort>
            <spirit:name>ARADDR</spirit:name>
          </spirit:logicalPort>
          <spirit:physicalPort>
            <spirit:name>s_axi_ctrl_mgmt_araddr</spirit:name>
          </spirit:physicalPort>
        </spirit:portMap>
        <spirit:portMap>
          <spirit:logicalPort>
            <spirit:name>ARPROT</spirit:name>
          </spirit:logicalPort>
          <spirit:physicalPort>
            <spirit:name>s_axi_ctrl_mgmt_arprot</spirit:name>
          </spirit:physicalPort>
        </spirit:portMap>
        <spirit:portMap>
          <spirit:logicalPort>
            <spirit:name>ARVALID</spirit:name>
          </spirit:logicalPort>
          <spirit:physicalPort>
            <spirit:name>s_axi_ctrl_mgmt_arvalid</spirit:name>
          </spirit:physicalPort>
        </spirit:portMap>
        <spirit:portMap>
          <spirit:logicalPort>
            <spirit:name>ARREADY</spirit:name>
          </spirit:logicalPort>
          <spirit:physicalPort>
            <spirit:name>s_axi_ctrl_mgmt_arready</spirit:name>
          </spirit:physicalPort>
        </spirit:portMap>
        <spirit:portMap>
          <spirit:logicalPort>
            <spirit:name>RDATA</spirit:name>
          </spirit:logicalPort>
          <spirit:physicalPort>
            <spirit:name>s_axi_ctrl_mgmt_rdata</spirit:name>
          </spirit:physicalPort>
        </spirit:portMap>
        <spirit:portMap>
          <spirit:logicalPort>
            <spirit:name>RRESP</spirit:name>
          </spirit:logicalPort>
          <spirit:physicalPort>
            <spirit:name>s_axi_ctrl_mgmt_rresp</spirit:name>
          </spirit:physicalPort>
        </spirit:portMap>
        <spirit:portMap>
          <spirit:logicalPort>
            <spirit:name>RVALID</spirit:name>
          </spirit:logicalPort>
          <spirit:physicalPort>
            <spirit:name>s_axi_ctrl_mgmt_rvalid</spirit:name>
          </spirit:physicalPort>
        </spirit:portMap>
        <spirit:portMap>
          <spirit:logicalPort>
            <spirit:name>RREADY</spirit:name>
          </spirit:logicalPort>
          <spirit:physicalPort>
            <spirit:name>s_axi_ctrl_mgmt_rready</spirit:name>
          </spirit:physicalPort>
        </spirit:portMap>
      </spirit:portMaps>
      <spirit:parameters>
        <spirit:parameter>
          <spirit:name>DATA_WIDTH</spirit:name>
          <spirit:value spirit:format="long" spirit:resolve="generated" spirit:id="BUSIFPARAM_VALUE.S_AXI_CTRL_MGMT.DATA_WIDTH">32</spirit:value>
          <spirit:vendorExtensions>
            <xilinx:parameterInfo>
              <xilinx:parameterUsage>none</xilinx:parameterUsage>
            </xilinx:parameterInfo>
          </spirit:vendorExtensions>
        </spirit:parameter>
        <spirit:parameter>
          <spirit:name>PROTOCOL</spirit:name>
          <spirit:value spirit:resolve="generated" spirit:id="BUSIFPARAM_VALUE.S_AXI_CTRL_MGMT.PROTOCOL">AXI4LITE</spirit:value>
          <spirit:vendorExtensions>
            <xilinx:parameterInfo>
              <xilinx:parameterUsage>none</xilinx:parameterUsage>
            </xilinx:parameterInfo>
          </spirit:vendorExtensions>
        </spirit:parameter>
        <spirit:parameter>
          <spirit:name>FREQ_HZ</spirit:name>
          <spirit:value spirit:format="long" spirit:resolve="generated" spirit:id="BUSIFPARAM_VALUE.S_AXI_CTRL_MGMT.FREQ_HZ">50000000</spirit:value>
          <spirit:vendorExtensions>
            <xilinx:parameterInfo>
              <xilinx:parameterUsage>none</xilinx:parameterUsage>
            </xilinx:parameterInfo>
          </spirit:vendorExtensions>
        </spirit:parameter>
        <spirit:parameter>
          <spirit:name>ID_WIDTH</spirit:name>
          <spirit:value spirit:format="long" spirit:resolve="generated" spirit:id="BUSIFPARAM_VALUE.S_AXI_CTRL_MGMT.ID_WIDTH">0</spirit:value>
          <spirit:vendorExtensions>
            <xilinx:parameterInfo>
              <xilinx:parameterUsage>none</xilinx:parameterUsage>
            </xilinx:parameterInfo>
          </spirit:vendorExtensions>
        </spirit:parameter>
        <spirit:parameter>
          <spirit:name>ADDR_WIDTH</spirit:name>
          <spirit:value spirit:format="long" spirit:resolve="generated" spirit:id="BUSIFPARAM_VALUE.S_AXI_CTRL_MGMT.ADDR_WIDTH">18</spirit:value>
          <spirit:vendorExtensions>
            <xilinx:parameterInfo>
              <xilinx:parameterUsage>none</xilinx:parameterUsage>
            </xilinx:parameterInfo>
          </spirit:vendorExtensions>
        </spirit:parameter>
        <spirit:parameter>
          <spirit:name>AWUSER_WIDTH</spirit:name>
          <spirit:value spirit:format="long" spirit:resolve="generated" spirit:id="BUSIFPARAM_VALUE.S_AXI_CTRL_MGMT.AWUSER_WIDTH">0</spirit:value>
          <spirit:vendorExtensions>
            <xilinx:parameterInfo>
              <xilinx:parameterUsage>none</xilinx:parameterUsage>
            </xilinx:parameterInfo>
          </spirit:vendorExtensions>
        </spirit:parameter>
        <spirit:parameter>
          <spirit:name>ARUSER_WIDTH</spirit:name>
          <spirit:value spirit:format="long" spirit:resolve="generated" spirit:id="BUSIFPARAM_VALUE.S_AXI_CTRL_MGMT.ARUSER_WIDTH">0</spirit:value>
          <spirit:vendorExtensions>
            <xilinx:parameterInfo>
              <xilinx:parameterUsage>none</xilinx:parameterUsage>
            </xilinx:parameterInfo>
          </spirit:vendorExtensions>
        </spirit:parameter>
        <spirit:parameter>
          <spirit:name>WUSER_WIDTH</spirit:name>
          <spirit:value spirit:format="long" spirit:resolve="generated" spirit:id="BUSIFPARAM_VALUE.S_AXI_CTRL_MGMT.WUSER_WIDTH">0</spirit:value>
          <spirit:vendorExtensions>
            <xilinx:parameterInfo>
              <xilinx:parameterUsage>none</xilinx:parameterUsage>
            </xilinx:parameterInfo>
          </spirit:vendorExtensions>
        </spirit:parameter>
        <spirit:parameter>
          <spirit:name>RUSER_WIDTH</spirit:name>
          <spirit:value spirit:format="long" spirit:resolve="generated" spirit:id="BUSIFPARAM_VALUE.S_AXI_CTRL_MGMT.RUSER_WIDTH">0</spirit:value>
          <spirit:vendorExtensions>
            <xilinx:parameterInfo>
              <xilinx:parameterUsage>none</xilinx:parameterUsage>
            </xilinx:parameterInfo>
          </spirit:vendorExtensions>
        </spirit:parameter>
        <spirit:parameter>
          <spirit:name>BUSER_WIDTH</spirit:name>
          <spirit:value spirit:format="long" spirit:resolve="generated" spirit:id="BUSIFPARAM_VALUE.S_AXI_CTRL_MGMT.BUSER_WIDTH">0</spirit:value>
          <spirit:vendorExtensions>
            <xilinx:parameterInfo>
              <xilinx:parameterUsage>none</xilinx:parameterUsage>
            </xilinx:parameterInfo>
          </spirit:vendorExtensions>
        </spirit:parameter>
        <spirit:parameter>
          <spirit:name>READ_WRITE_MODE</spirit:name>
          <spirit:value spirit:resolve="generated" spirit:id="BUSIFPARAM_VALUE.S_AXI_CTRL_MGMT.READ_WRITE_MODE">READ_WRITE</spirit:value>
          <spirit:vendorExtensions>
            <xilinx:parameterInfo>
              <xilinx:parameterUsage>none</xilinx:parameterUsage>
            </xilinx:parameterInfo>
          </spirit:vendorExtensions>
        </spirit:parameter>
        <spirit:parameter>
          <spirit:name>HAS_BURST</spirit:name>
          <spirit:value spirit:format="long" spirit:resolve="generated" spirit:id="BUSIFPARAM_VALUE.S_AXI_CTRL_MGMT.HAS_BURST">0</spirit:value>
          <spirit:vendorExtensions>
            <xilinx:parameterInfo>
              <xilinx:parameterUsage>none</xilinx:parameterUsage>
            </xilinx:parameterInfo>
          </spirit:vendorExtensions>
        </spirit:parameter>
        <spirit:parameter>
          <spirit:name>HAS_LOCK</spirit:name>
          <spirit:value spirit:format="long" spirit:resolve="generated" spirit:id="BUSIFPARAM_VALUE.S_AXI_CTRL_MGMT.HAS_LOCK">0</spirit:value>
          <spirit:vendorExtensions>
            <xilinx:parameterInfo>
              <xilinx:parameterUsage>none</xilinx:parameterUsage>
            </xilinx:parameterInfo>
          </spirit:vendorExtensions>
        </spirit:parameter>
        <spirit:parameter>
          <spirit:name>HAS_PROT</spirit:name>
          <spirit:value spirit:format="long" spirit:resolve="generated" spirit:id="BUSIFPARAM_VALUE.S_AXI_CTRL_MGMT.HAS_PROT">0</spirit:value>
          <spirit:vendorExtensions>
            <xilinx:parameterInfo>
              <xilinx:parameterUsage>none</xilinx:parameterUsage>
            </xilinx:parameterInfo>
          </spirit:vendorExtensions>
        </spirit:parameter>
        <spirit:parameter>
          <spirit:name>HAS_CACHE</spirit:name>
          <spirit:value spirit:format="long" spirit:resolve="generated" spirit:id="BUSIFPARAM_VALUE.S_AXI_CTRL_MGMT.HAS_CACHE">0</spirit:value>
          <spirit:vendorExtensions>
            <xilinx:parameterInfo>
              <xilinx:parameterUsage>none</xilinx:parameterUsage>
            </xilinx:parameterInfo>
          </spirit:vendorExtensions>
        </spirit:parameter>
        <spirit:parameter>
          <spirit:name>HAS_QOS</spirit:name>
          <spirit:value spirit:format="long" spirit:resolve="generated" spirit:id="BUSIFPARAM_VALUE.S_AXI_CTRL_MGMT.HAS_QOS">0</spirit:value>
          <spirit:vendorExtensions>
            <xilinx:parameterInfo>
              <xilinx:parameterUsage>none</xilinx:parameterUsage>
            </xilinx:parameterInfo>
          </spirit:vendorExtensions>
        </spirit:parameter>
        <spirit:parameter>
          <spirit:name>HAS_REGION</spirit:name>
          <spirit:value spirit:format="long" spirit:resolve="generated" spirit:id="BUSIFPARAM_VALUE.S_AXI_CTRL_MGMT.HAS_REGION">0</spirit:value>
          <spirit:vendorExtensions>
            <xilinx:parameterInfo>
              <xilinx:parameterUsage>none</xilinx:parameterUsage>
            </xilinx:parameterInfo>
          </spirit:vendorExtensions>
        </spirit:parameter>
        <spirit:parameter>
          <spirit:name>HAS_WSTRB</spirit:name>
          <spirit:value spirit:format="long" spirit:resolve="generated" spirit:id="BUSIFPARAM_VALUE.S_AXI_CTRL_MGMT.HAS_WSTRB">1</spirit:value>
          <spirit:vendorExtensions>
            <xilinx:parameterInfo>
              <xilinx:parameterUsage>none</xilinx:parameterUsage>
            </xilinx:parameterInfo>
          </spirit:vendorExtensions>
        </spirit:parameter>
        <spirit:parameter>
          <spirit:name>HAS_BRESP</spirit:name>
          <spirit:value spirit:format="long" spirit:resolve="generated" spirit:id="BUSIFPARAM_VALUE.S_AXI_CTRL_MGMT.HAS_BRESP">1</spirit:value>
          <spirit:vendorExtensions>
            <xilinx:parameterInfo>
              <xilinx:parameterUsage>none</xilinx:parameterUsage>
            </xilinx:parameterInfo>
          </spirit:vendorExtensions>
        </spirit:parameter>
        <spirit:parameter>
          <spirit:name>HAS_RRESP</spirit:name>
          <spirit:value spirit:format="long" spirit:resolve="generated" spirit:id="BUSIFPARAM_VALUE.S_AXI_CTRL_MGMT.HAS_RRESP">1</spirit:value>
          <spirit:vendorExtensions>
            <xilinx:parameterInfo>
              <xilinx:parameterUsage>none</xilinx:parameterUsage>
            </xilinx:parameterInfo>
          </spirit:vendorExtensions>
        </spirit:parameter>
        <spirit:parameter>
          <spirit:name>SUPPORTS_NARROW_BURST</spirit:name>
          <spirit:value spirit:format="long" spirit:resolve="generated" spirit:id="BUSIFPARAM_VALUE.S_AXI_CTRL_MGMT.SUPPORTS_NARROW_BURST">0</spirit:value>
          <spirit:vendorExtensions>
            <xilinx:parameterInfo>
              <xilinx:parameterUsage>none</xilinx:parameterUsage>
            </xilinx:parameterInfo>
          </spirit:vendorExtensions>
        </spirit:parameter>
        <spirit:parameter>
          <spirit:name>NUM_READ_OUTSTANDING</spirit:name>
          <spirit:value spirit:format="long" spirit:resolve="generated" spirit:id="BUSIFPARAM_VALUE.S_AXI_CTRL_MGMT.NUM_READ_OUTSTANDING">2</spirit:value>
          <spirit:vendorExtensions>
            <xilinx:parameterInfo>
              <xilinx:parameterUsage>none</xilinx:parameterUsage>
            </xilinx:parameterInfo>
          </spirit:vendorExtensions>
        </spirit:parameter>
        <spirit:parameter>
          <spirit:name>NUM_WRITE_OUTSTANDING</spirit:name>
          <spirit:value spirit:format="long" spirit:resolve="generated" spirit:id="BUSIFPARAM_VALUE.S_AXI_CTRL_MGMT.NUM_WRITE_OUTSTANDING">2</spirit:value>
          <spirit:vendorExtensions>
            <xilinx:parameterInfo>
              <xilinx:parameterUsage>none</xilinx:parameterUsage>
            </xilinx:parameterInfo>
          </spirit:vendorExtensions>
        </spirit:parameter>
        <spirit:parameter>
          <spirit:name>MAX_BURST_LENGTH</spirit:name>
          <spirit:value spirit:format="long" spirit:resolve="generated" spirit:id="BUSIFPARAM_VALUE.S_AXI_CTRL_MGMT.MAX_BURST_LENGTH">1</spirit:value>
          <spirit:vendorExtensions>
            <xilinx:parameterInfo>
              <xilinx:parameterUsage>none</xilinx:parameterUsage>
            </xilinx:parameterInfo>
          </spirit:vendorExtensions>
        </spirit:parameter>
        <spirit:parameter>
          <spirit:name>PHASE</spirit:name>
          <spirit:value spirit:format="float" spirit:resolve="generated" spirit:id="BUSIFPARAM_VALUE.S_AXI_CTRL_MGMT.PHASE">0.0</spirit:value>
          <spirit:vendorExtensions>
            <xilinx:parameterInfo>
              <xilinx:parameterUsage>none</xilinx:parameterUsage>
            </xilinx:parameterInfo>
          </spirit:vendorExtensions>
        </spirit:parameter>
        <spirit:parameter>
          <spirit:name>CLK_DOMAIN</spirit:name>
          <spirit:value spirit:resolve="generated" spirit:id="BUSIFPARAM_VALUE.S_AXI_CTRL_MGMT.CLK_DOMAIN">PCIe_Bridge_ICAP_complex_clk_wiz_0_0_clk_out_125M</spirit:value>
          <spirit:vendorExtensions>
            <xilinx:parameterInfo>
              <xilinx:parameterUsage>none</xilinx:parameterUsage>
            </xilinx:parameterInfo>
          </spirit:vendorExtensions>
        </spirit:parameter>
        <spirit:parameter>
          <spirit:name>NUM_READ_THREADS</spirit:name>
          <spirit:value spirit:format="long" spirit:resolve="generated" spirit:id="BUSIFPARAM_VALUE.S_AXI_CTRL_MGMT.NUM_READ_THREADS">1</spirit:value>
          <spirit:vendorExtensions>
            <xilinx:parameterInfo>
              <xilinx:parameterUsage>none</xilinx:parameterUsage>
            </xilinx:parameterInfo>
          </spirit:vendorExtensions>
        </spirit:parameter>
        <spirit:parameter>
          <spirit:name>NUM_WRITE_THREADS</spirit:name>
          <spirit:value spirit:format="long" spirit:resolve="generated" spirit:id="BUSIFPARAM_VALUE.S_AXI_CTRL_MGMT.NUM_WRITE_THREADS">1</spirit:value>
          <spirit:vendorExtensions>
            <xilinx:parameterInfo>
              <xilinx:parameterUsage>none</xilinx:parameterUsage>
            </xilinx:parameterInfo>
          </spirit:vendorExtensions>
        </spirit:parameter>
        <spirit:parameter>
          <spirit:name>RUSER_BITS_PER_BYTE</spirit:name>
          <spirit:value spirit:format="long" spirit:resolve="generated" spirit:id="BUSIFPARAM_VALUE.S_AXI_CTRL_MGMT.RUSER_BITS_PER_BYTE">0</spirit:value>
          <spirit:vendorExtensions>
            <xilinx:parameterInfo>
              <xilinx:parameterUsage>none</xilinx:parameterUsage>
            </xilinx:parameterInfo>
          </spirit:vendorExtensions>
        </spirit:parameter>
        <spirit:parameter>
          <spirit:name>WUSER_BITS_PER_BYTE</spirit:name>
          <spirit:value spirit:format="long" spirit:resolve="generated" spirit:id="BUSIFPARAM_VALUE.S_AXI_CTRL_MGMT.WUSER_BITS_PER_BYTE">0</spirit:value>
          <spirit:vendorExtensions>
            <xilinx:parameterInfo>
              <xilinx:parameterUsage>none</xilinx:parameterUsage>
            </xilinx:parameterInfo>
          </spirit:vendorExtensions>
        </spirit:parameter>
        <spirit:parameter>
          <spirit:name>INSERT_VIP</spirit:name>
          <spirit:value spirit:format="long" spirit:resolve="user" spirit:id="BUSIFPARAM_VALUE.S_AXI_CTRL_MGMT.INSERT_VIP">1</spirit:value>
          <spirit:vendorExtensions>
            <xilinx:parameterInfo>
              <xilinx:parameterUsage>simulation.rtl</xilinx:parameterUsage>
            </xilinx:parameterInfo>
          </spirit:vendorExtensions>
        </spirit:parameter>
      </spirit:parameters>
    </spirit:busInterface>
    <spirit:busInterface>
      <spirit:name>mdm_mbdebug</spirit:name>
      <spirit:busType spirit:vendor="xilinx.com" spirit:library="interface" spirit:name="mbdebug" spirit:version="3.0"/>
      <spirit:abstractionType spirit:vendor="xilinx.com" spirit:library="interface" spirit:name="mbdebug_rtl" spirit:version="3.0"/>
      <spirit:slave/>
      <spirit:portMaps>
        <spirit:portMap>
          <spirit:logicalPort>
            <spirit:name>CAPTURE</spirit:name>
          </spirit:logicalPort>
          <spirit:physicalPort>
            <spirit:name>mdm_mbdebug_capture</spirit:name>
          </spirit:physicalPort>
        </spirit:portMap>
        <spirit:portMap>
          <spirit:logicalPort>
            <spirit:name>CLK</spirit:name>
          </spirit:logicalPort>
          <spirit:physicalPort>
            <spirit:name>mdm_mbdebug_clk</spirit:name>
          </spirit:physicalPort>
        </spirit:portMap>
        <spirit:portMap>
          <spirit:logicalPort>
            <spirit:name>DISABLE</spirit:name>
          </spirit:logicalPort>
          <spirit:physicalPort>
            <spirit:name>mdm_mbdebug_disable</spirit:name>
          </spirit:physicalPort>
        </spirit:portMap>
        <spirit:portMap>
          <spirit:logicalPort>
            <spirit:name>REG_EN</spirit:name>
          </spirit:logicalPort>
          <spirit:physicalPort>
            <spirit:name>mdm_mbdebug_reg_en</spirit:name>
          </spirit:physicalPort>
        </spirit:portMap>
        <spirit:portMap>
          <spirit:logicalPort>
            <spirit:name>RST</spirit:name>
          </spirit:logicalPort>
          <spirit:physicalPort>
            <spirit:name>mdm_mbdebug_rst</spirit:name>
          </spirit:physicalPort>
        </spirit:portMap>
        <spirit:portMap>
          <spirit:logicalPort>
            <spirit:name>SHIFT</spirit:name>
          </spirit:logicalPort>
          <spirit:physicalPort>
            <spirit:name>mdm_mbdebug_shift</spirit:name>
          </spirit:physicalPort>
        </spirit:portMap>
        <spirit:portMap>
          <spirit:logicalPort>
            <spirit:name>TDI</spirit:name>
          </spirit:logicalPort>
          <spirit:physicalPort>
            <spirit:name>mdm_mbdebug_tdi</spirit:name>
          </spirit:physicalPort>
        </spirit:portMap>
        <spirit:portMap>
          <spirit:logicalPort>
            <spirit:name>TDO</spirit:name>
          </spirit:logicalPort>
          <spirit:physicalPort>
            <spirit:name>mdm_mbdebug_tdo</spirit:name>
          </spirit:physicalPort>
        </spirit:portMap>
        <spirit:portMap>
          <spirit:logicalPort>
            <spirit:name>UPDATE</spirit:name>
          </spirit:logicalPort>
          <spirit:physicalPort>
            <spirit:name>mdm_mbdebug_update</spirit:name>
          </spirit:physicalPort>
        </spirit:portMap>
      </spirit:portMaps>
    </spirit:busInterface>
    <spirit:busInterface>
      <spirit:name>satellite_uart</spirit:name>
      <spirit:busType spirit:vendor="xilinx.com" spirit:library="interface" spirit:name="uart" spirit:version="1.0"/>
      <spirit:abstractionType spirit:vendor="xilinx.com" spirit:library="interface" spirit:name="uart_rtl" spirit:version="1.0"/>
      <spirit:master/>
      <spirit:portMaps>
        <spirit:portMap>
          <spirit:logicalPort>
            <spirit:name>RxD</spirit:name>
          </spirit:logicalPort>
          <spirit:physicalPort>
            <spirit:name>satellite_uart_rxd</spirit:name>
          </spirit:physicalPort>
        </spirit:portMap>
        <spirit:portMap>
          <spirit:logicalPort>
            <spirit:name>TxD</spirit:name>
          </spirit:logicalPort>
          <spirit:physicalPort>
            <spirit:name>satellite_uart_txd</spirit:name>
          </spirit:physicalPort>
        </spirit:portMap>
      </spirit:portMaps>
    </spirit:busInterface>
    <spirit:busInterface>
      <spirit:name>satellite_gpio</spirit:name>
      <spirit:busType spirit:vendor="xilinx.com" spirit:library="interface" spirit:name="gpio" spirit:version="1.0"/>
      <spirit:abstractionType spirit:vendor="xilinx.com" spirit:library="interface" spirit:name="gpio_rtl" spirit:version="1.0"/>
      <spirit:master/>
      <spirit:portMaps>
        <spirit:portMap>
          <spirit:logicalPort>
            <spirit:name>TRI_I</spirit:name>
          </spirit:logicalPort>
          <spirit:physicalPort>
            <spirit:name>satellite_gpio_tri_i</spirit:name>
          </spirit:physicalPort>
        </spirit:portMap>
        <spirit:portMap>
          <spirit:logicalPort>
            <spirit:name>TRI_O</spirit:name>
          </spirit:logicalPort>
          <spirit:physicalPort>
            <spirit:name>satellite_gpio_tri_o</spirit:name>
          </spirit:physicalPort>
        </spirit:portMap>
        <spirit:portMap>
          <spirit:logicalPort>
            <spirit:name>TRI_T</spirit:name>
          </spirit:logicalPort>
          <spirit:physicalPort>
            <spirit:name>satellite_gpio_tri_t</spirit:name>
          </spirit:physicalPort>
        </spirit:portMap>
      </spirit:portMaps>
    </spirit:busInterface>
  </spirit:busInterfaces>
  <spirit:memoryMaps>
    <spirit:memoryMap>
      <spirit:name>s_axi_ctrl_mgmt</spirit:name>
      <spirit:addressBlock>
        <spirit:name>Mem</spirit:name>
        <spirit:baseAddress spirit:format="bitString" spirit:resolve="generated">0x00000</spirit:baseAddress>
        <spirit:range spirit:format="bitString">0x00040000</spirit:range>
        <spirit:width spirit:format="long">32</spirit:width>
        <spirit:usage>memory</spirit:usage>
      </spirit:addressBlock>
    </spirit:memoryMap>
  </spirit:memoryMaps>
  <spirit:model>
    <spirit:views>
      <spirit:view>
        <spirit:name>xilinx_elaborateports</spirit:name>
        <spirit:displayName>Elaborate Ports</spirit:displayName>
        <spirit:envIdentifier>:vivado.xilinx.com:elaborate.ports</spirit:envIdentifier>
        <spirit:fileSetRef>
          <spirit:localName>xilinx_elaborateports_view_fileset</spirit:localName>
        </spirit:fileSetRef>
        <spirit:parameters>
          <spirit:parameter>
            <spirit:name>outputProductCRC</spirit:name>
            <spirit:value>9:ce1ce16a</spirit:value>
          </spirit:parameter>
        </spirit:parameters>
      </spirit:view>
      <spirit:view>
        <spirit:name>xilinx_elaboratebd</spirit:name>
        <spirit:displayName>Elaborate BD</spirit:displayName>
        <spirit:envIdentifier>:vivado.xilinx.com:elaborate.bd</spirit:envIdentifier>
        <spirit:fileSetRef>
          <spirit:localName>xilinx_elaboratebd_view_fileset</spirit:localName>
        </spirit:fileSetRef>
        <spirit:parameters>
          <spirit:parameter>
            <spirit:name>outputProductCRC</spirit:name>
            <spirit:value>9:76c153fb</spirit:value>
          </spirit:parameter>
        </spirit:parameters>
      </spirit:view>
    </spirit:views>
    <spirit:ports>
      <spirit:port>
        <spirit:name>aclk_ctrl</spirit:name>
        <spirit:wire>
          <spirit:direction>in</spirit:direction>
          <spirit:wireTypeDefs>
            <spirit:wireTypeDef>
              <spirit:typeName>std_logic</spirit:typeName>
              <spirit:viewNameRef>xilinx_elaborateports</spirit:viewNameRef>
            </spirit:wireTypeDef>
          </spirit:wireTypeDefs>
        </spirit:wire>
      </spirit:port>
      <spirit:port>
        <spirit:name>aresetn_ctrl</spirit:name>
        <spirit:wire>
          <spirit:direction>in</spirit:direction>
          <spirit:wireTypeDefs>
            <spirit:wireTypeDef>
              <spirit:typeName>std_logic</spirit:typeName>
              <spirit:viewNameRef>xilinx_elaborateports</spirit:viewNameRef>
            </spirit:wireTypeDef>
          </spirit:wireTypeDefs>
        </spirit:wire>
      </spirit:port>
      <spirit:port>
        <spirit:name>mdm_debug_sys_rst</spirit:name>
        <spirit:wire>
          <spirit:direction>in</spirit:direction>
          <spirit:wireTypeDefs>
            <spirit:wireTypeDef>
              <spirit:typeName>std_logic</spirit:typeName>
              <spirit:viewNameRef>xilinx_elaborateports</spirit:viewNameRef>
            </spirit:wireTypeDef>
          </spirit:wireTypeDefs>
          <spirit:driver>
            <spirit:defaultValue spirit:format="long">0</spirit:defaultValue>
          </spirit:driver>
        </spirit:wire>
      </spirit:port>
      <spirit:port>
        <spirit:name>interrupt_hbm_cattrip</spirit:name>
        <spirit:wire>
          <spirit:direction>in</spirit:direction>
          <spirit:vector>
            <spirit:left spirit:format="long">0</spirit:left>
            <spirit:right spirit:format="long">0</spirit:right>
          </spirit:vector>
          <spirit:wireTypeDefs>
            <spirit:wireTypeDef>
              <spirit:typeName>std_logic_vector</spirit:typeName>
              <spirit:viewNameRef>xilinx_elaborateports</spirit:viewNameRef>
            </spirit:wireTypeDef>
          </spirit:wireTypeDefs>
          <spirit:driver>
            <spirit:defaultValue spirit:format="long">0</spirit:defaultValue>
          </spirit:driver>
        </spirit:wire>
      </spirit:port>
      <spirit:port>
        <spirit:name>hbm_temp_1</spirit:name>
        <spirit:wire>
          <spirit:direction>in</spirit:direction>
          <spirit:vector>
            <spirit:left spirit:format="long">6</spirit:left>
            <spirit:right spirit:format="long">0</spirit:right>
          </spirit:vector>
          <spirit:wireTypeDefs>
            <spirit:wireTypeDef>
              <spirit:typeName>std_logic_vector</spirit:typeName>
              <spirit:viewNameRef>xilinx_elaborateports</spirit:viewNameRef>
            </spirit:wireTypeDef>
          </spirit:wireTypeDefs>
          <spirit:driver>
            <spirit:defaultValue spirit:format="long">0</spirit:defaultValue>
          </spirit:driver>
        </spirit:wire>
      </spirit:port>
      <spirit:port>
        <spirit:name>hbm_temp_2</spirit:name>
        <spirit:wire>
          <spirit:direction>in</spirit:direction>
          <spirit:vector>
            <spirit:left spirit:format="long">6</spirit:left>
            <spirit:right spirit:format="long">0</spirit:right>
          </spirit:vector>
          <spirit:wireTypeDefs>
            <spirit:wireTypeDef>
              <spirit:typeName>std_logic_vector</spirit:typeName>
              <spirit:viewNameRef>xilinx_elaborateports</spirit:viewNameRef>
            </spirit:wireTypeDef>
          </spirit:wireTypeDefs>
          <spirit:driver>
            <spirit:defaultValue spirit:format="long">0</spirit:defaultValue>
          </spirit:driver>
        </spirit:wire>
      </spirit:port>
      <spirit:port>
        <spirit:name>interrupt_host</spirit:name>
        <spirit:wire>
          <spirit:direction>out</spirit:direction>
          <spirit:wireTypeDefs>
            <spirit:wireTypeDef>
              <spirit:typeName>std_logic</spirit:typeName>
              <spirit:viewNameRef>xilinx_elaborateports</spirit:viewNameRef>
            </spirit:wireTypeDef>
          </spirit:wireTypeDefs>
        </spirit:wire>
      </spirit:port>
      <spirit:port>
        <spirit:name>qsfp0_modprs_l</spirit:name>
        <spirit:wire>
          <spirit:direction>in</spirit:direction>
          <spirit:vector>
            <spirit:left spirit:format="long">0</spirit:left>
            <spirit:right spirit:format="long">0</spirit:right>
          </spirit:vector>
          <spirit:wireTypeDefs>
            <spirit:wireTypeDef>
              <spirit:typeName>std_logic_vector</spirit:typeName>
              <spirit:viewNameRef>xilinx_elaborateports</spirit:viewNameRef>
            </spirit:wireTypeDef>
          </spirit:wireTypeDefs>
          <spirit:driver>
            <spirit:defaultValue spirit:format="long">0</spirit:defaultValue>
          </spirit:driver>
        </spirit:wire>
      </spirit:port>
      <spirit:port>
        <spirit:name>qsfp1_modprs_l</spirit:name>
        <spirit:wire>
          <spirit:direction>in</spirit:direction>
          <spirit:vector>
            <spirit:left spirit:format="long">0</spirit:left>
            <spirit:right spirit:format="long">0</spirit:right>
          </spirit:vector>
          <spirit:wireTypeDefs>
            <spirit:wireTypeDef>
              <spirit:typeName>std_logic_vector</spirit:typeName>
              <spirit:viewNameRef>xilinx_elaborateports</spirit:viewNameRef>
            </spirit:wireTypeDef>
          </spirit:wireTypeDefs>
          <spirit:driver>
            <spirit:defaultValue spirit:format="long">0</spirit:defaultValue>
          </spirit:driver>
        </spirit:wire>
      </spirit:port>
      <spirit:port>
        <spirit:name>qsfp0_int_l</spirit:name>
        <spirit:wire>
          <spirit:direction>in</spirit:direction>
          <spirit:vector>
            <spirit:left spirit:format="long">0</spirit:left>
            <spirit:right spirit:format="long">0</spirit:right>
          </spirit:vector>
          <spirit:wireTypeDefs>
            <spirit:wireTypeDef>
              <spirit:typeName>std_logic_vector</spirit:typeName>
              <spirit:viewNameRef>xilinx_elaborateports</spirit:viewNameRef>
            </spirit:wireTypeDef>
          </spirit:wireTypeDefs>
          <spirit:driver>
            <spirit:defaultValue spirit:format="long">0</spirit:defaultValue>
          </spirit:driver>
        </spirit:wire>
      </spirit:port>
      <spirit:port>
        <spirit:name>qsfp1_int_l</spirit:name>
        <spirit:wire>
          <spirit:direction>in</spirit:direction>
          <spirit:vector>
            <spirit:left spirit:format="long">0</spirit:left>
            <spirit:right spirit:format="long">0</spirit:right>
          </spirit:vector>
          <spirit:wireTypeDefs>
            <spirit:wireTypeDef>
              <spirit:typeName>std_logic_vector</spirit:typeName>
              <spirit:viewNameRef>xilinx_elaborateports</spirit:viewNameRef>
            </spirit:wireTypeDef>
          </spirit:wireTypeDefs>
          <spirit:driver>
            <spirit:defaultValue spirit:format="long">0</spirit:defaultValue>
          </spirit:driver>
        </spirit:wire>
      </spirit:port>
      <spirit:port>
        <spirit:name>qsfp0_lpmode</spirit:name>
        <spirit:wire>
          <spirit:direction>out</spirit:direction>
          <spirit:vector>
            <spirit:left spirit:format="long">0</spirit:left>
            <spirit:right spirit:format="long">0</spirit:right>
          </spirit:vector>
          <spirit:wireTypeDefs>
            <spirit:wireTypeDef>
              <spirit:typeName>std_logic_vector</spirit:typeName>
              <spirit:viewNameRef>xilinx_elaborateports</spirit:viewNameRef>
            </spirit:wireTypeDef>
          </spirit:wireTypeDefs>
        </spirit:wire>
      </spirit:port>
      <spirit:port>
        <spirit:name>qsfp1_lpmode</spirit:name>
        <spirit:wire>
          <spirit:direction>out</spirit:direction>
          <spirit:vector>
            <spirit:left spirit:format="long">0</spirit:left>
            <spirit:right spirit:format="long">0</spirit:right>
          </spirit:vector>
          <spirit:wireTypeDefs>
            <spirit:wireTypeDef>
              <spirit:typeName>std_logic_vector</spirit:typeName>
              <spirit:viewNameRef>xilinx_elaborateports</spirit:viewNameRef>
            </spirit:wireTypeDef>
          </spirit:wireTypeDefs>
        </spirit:wire>
      </spirit:port>
      <spirit:port>
        <spirit:name>qsfp0_modsel_l</spirit:name>
        <spirit:wire>
          <spirit:direction>out</spirit:direction>
          <spirit:vector>
            <spirit:left spirit:format="long">0</spirit:left>
            <spirit:right spirit:format="long">0</spirit:right>
          </spirit:vector>
          <spirit:wireTypeDefs>
            <spirit:wireTypeDef>
              <spirit:typeName>std_logic_vector</spirit:typeName>
              <spirit:viewNameRef>xilinx_elaborateports</spirit:viewNameRef>
            </spirit:wireTypeDef>
          </spirit:wireTypeDefs>
        </spirit:wire>
      </spirit:port>
      <spirit:port>
        <spirit:name>qsfp1_modsel_l</spirit:name>
        <spirit:wire>
          <spirit:direction>out</spirit:direction>
          <spirit:vector>
            <spirit:left spirit:format="long">0</spirit:left>
            <spirit:right spirit:format="long">0</spirit:right>
          </spirit:vector>
          <spirit:wireTypeDefs>
            <spirit:wireTypeDef>
              <spirit:typeName>std_logic_vector</spirit:typeName>
              <spirit:viewNameRef>xilinx_elaborateports</spirit:viewNameRef>
            </spirit:wireTypeDef>
          </spirit:wireTypeDefs>
        </spirit:wire>
      </spirit:port>
      <spirit:port>
        <spirit:name>qsfp0_reset_l</spirit:name>
        <spirit:wire>
          <spirit:direction>out</spirit:direction>
          <spirit:vector>
            <spirit:left spirit:format="long">0</spirit:left>
            <spirit:right spirit:format="long">0</spirit:right>
          </spirit:vector>
          <spirit:wireTypeDefs>
            <spirit:wireTypeDef>
              <spirit:typeName>std_logic_vector</spirit:typeName>
              <spirit:viewNameRef>xilinx_elaborateports</spirit:viewNameRef>
            </spirit:wireTypeDef>
          </spirit:wireTypeDefs>
        </spirit:wire>
      </spirit:port>
      <spirit:port>
        <spirit:name>qsfp1_reset_l</spirit:name>
        <spirit:wire>
          <spirit:direction>out</spirit:direction>
          <spirit:vector>
            <spirit:left spirit:format="long">0</spirit:left>
            <spirit:right spirit:format="long">0</spirit:right>
          </spirit:vector>
          <spirit:wireTypeDefs>
            <spirit:wireTypeDef>
              <spirit:typeName>std_logic_vector</spirit:typeName>
              <spirit:viewNameRef>xilinx_elaborateports</spirit:viewNameRef>
            </spirit:wireTypeDef>
          </spirit:wireTypeDefs>
        </spirit:wire>
      </spirit:port>
      <spirit:port>
        <spirit:name>mdm_mbdebug_capture</spirit:name>
        <spirit:wire>
          <spirit:direction>in</spirit:direction>
          <spirit:wireTypeDefs>
            <spirit:wireTypeDef>
              <spirit:typeName>std_logic</spirit:typeName>
              <spirit:viewNameRef>xilinx_elaborateports</spirit:viewNameRef>
            </spirit:wireTypeDef>
          </spirit:wireTypeDefs>
          <spirit:driver>
            <spirit:defaultValue spirit:format="long">0</spirit:defaultValue>
          </spirit:driver>
        </spirit:wire>
      </spirit:port>
      <spirit:port>
        <spirit:name>mdm_mbdebug_clk</spirit:name>
        <spirit:wire>
          <spirit:direction>in</spirit:direction>
          <spirit:wireTypeDefs>
            <spirit:wireTypeDef>
              <spirit:typeName>std_logic</spirit:typeName>
              <spirit:viewNameRef>xilinx_elaborateports</spirit:viewNameRef>
            </spirit:wireTypeDef>
          </spirit:wireTypeDefs>
          <spirit:driver>
            <spirit:defaultValue spirit:format="long">0</spirit:defaultValue>
          </spirit:driver>
        </spirit:wire>
      </spirit:port>
      <spirit:port>
        <spirit:name>mdm_mbdebug_disable</spirit:name>
        <spirit:wire>
          <spirit:direction>in</spirit:direction>
          <spirit:wireTypeDefs>
            <spirit:wireTypeDef>
              <spirit:typeName>std_logic</spirit:typeName>
              <spirit:viewNameRef>xilinx_elaborateports</spirit:viewNameRef>
            </spirit:wireTypeDef>
          </spirit:wireTypeDefs>
          <spirit:driver>
            <spirit:defaultValue spirit:format="long">0</spirit:defaultValue>
          </spirit:driver>
        </spirit:wire>
      </spirit:port>
      <spirit:port>
        <spirit:name>mdm_mbdebug_reg_en</spirit:name>
        <spirit:wire>
          <spirit:direction>in</spirit:direction>
          <spirit:vector>
            <spirit:left spirit:format="long">0</spirit:left>
            <spirit:right spirit:format="long">7</spirit:right>
          </spirit:vector>
          <spirit:wireTypeDefs>
            <spirit:wireTypeDef>
              <spirit:typeName>std_logic_vector</spirit:typeName>
              <spirit:viewNameRef>xilinx_elaborateports</spirit:viewNameRef>
            </spirit:wireTypeDef>
          </spirit:wireTypeDefs>
          <spirit:driver>
            <spirit:defaultValue spirit:format="long">0</spirit:defaultValue>
          </spirit:driver>
        </spirit:wire>
      </spirit:port>
      <spirit:port>
        <spirit:name>mdm_mbdebug_rst</spirit:name>
        <spirit:wire>
          <spirit:direction>in</spirit:direction>
          <spirit:wireTypeDefs>
            <spirit:wireTypeDef>
              <spirit:typeName>std_logic</spirit:typeName>
              <spirit:viewNameRef>xilinx_elaborateports</spirit:viewNameRef>
            </spirit:wireTypeDef>
          </spirit:wireTypeDefs>
          <spirit:driver>
            <spirit:defaultValue spirit:format="long">0</spirit:defaultValue>
          </spirit:driver>
        </spirit:wire>
      </spirit:port>
      <spirit:port>
        <spirit:name>mdm_mbdebug_shift</spirit:name>
        <spirit:wire>
          <spirit:direction>in</spirit:direction>
          <spirit:wireTypeDefs>
            <spirit:wireTypeDef>
              <spirit:typeName>std_logic</spirit:typeName>
              <spirit:viewNameRef>xilinx_elaborateports</spirit:viewNameRef>
            </spirit:wireTypeDef>
          </spirit:wireTypeDefs>
          <spirit:driver>
            <spirit:defaultValue spirit:format="long">0</spirit:defaultValue>
          </spirit:driver>
        </spirit:wire>
      </spirit:port>
      <spirit:port>
        <spirit:name>mdm_mbdebug_tdi</spirit:name>
        <spirit:wire>
          <spirit:direction>in</spirit:direction>
          <spirit:wireTypeDefs>
            <spirit:wireTypeDef>
              <spirit:typeName>std_logic</spirit:typeName>
              <spirit:viewNameRef>xilinx_elaborateports</spirit:viewNameRef>
            </spirit:wireTypeDef>
          </spirit:wireTypeDefs>
          <spirit:driver>
            <spirit:defaultValue spirit:format="long">0</spirit:defaultValue>
          </spirit:driver>
        </spirit:wire>
      </spirit:port>
      <spirit:port>
        <spirit:name>mdm_mbdebug_tdo</spirit:name>
        <spirit:wire>
          <spirit:direction>out</spirit:direction>
          <spirit:wireTypeDefs>
            <spirit:wireTypeDef>
              <spirit:typeName>std_logic</spirit:typeName>
              <spirit:viewNameRef>xilinx_elaborateports</spirit:viewNameRef>
            </spirit:wireTypeDef>
          </spirit:wireTypeDefs>
        </spirit:wire>
      </spirit:port>
      <spirit:port>
        <spirit:name>mdm_mbdebug_update</spirit:name>
        <spirit:wire>
          <spirit:direction>in</spirit:direction>
          <spirit:wireTypeDefs>
            <spirit:wireTypeDef>
              <spirit:typeName>std_logic</spirit:typeName>
              <spirit:viewNameRef>xilinx_elaborateports</spirit:viewNameRef>
            </spirit:wireTypeDef>
          </spirit:wireTypeDefs>
          <spirit:driver>
            <spirit:defaultValue spirit:format="long">0</spirit:defaultValue>
          </spirit:driver>
        </spirit:wire>
      </spirit:port>
      <spirit:port>
        <spirit:name>satellite_uart_rxd</spirit:name>
        <spirit:wire>
          <spirit:direction>in</spirit:direction>
          <spirit:wireTypeDefs>
            <spirit:wireTypeDef>
              <spirit:typeName>std_logic</spirit:typeName>
              <spirit:viewNameRef>xilinx_elaborateports</spirit:viewNameRef>
            </spirit:wireTypeDef>
          </spirit:wireTypeDefs>
          <spirit:driver>
            <spirit:defaultValue spirit:format="long">0</spirit:defaultValue>
          </spirit:driver>
        </spirit:wire>
      </spirit:port>
      <spirit:port>
        <spirit:name>satellite_uart_txd</spirit:name>
        <spirit:wire>
          <spirit:direction>out</spirit:direction>
          <spirit:wireTypeDefs>
            <spirit:wireTypeDef>
              <spirit:typeName>std_logic</spirit:typeName>
              <spirit:viewNameRef>xilinx_elaborateports</spirit:viewNameRef>
            </spirit:wireTypeDef>
          </spirit:wireTypeDefs>
        </spirit:wire>
      </spirit:port>
      <spirit:port>
        <spirit:name>s_axi_ctrl_mgmt_awaddr</spirit:name>
        <spirit:wire>
          <spirit:direction>in</spirit:direction>
          <spirit:vector>
            <spirit:left spirit:format="long">17</spirit:left>
            <spirit:right spirit:format="long">0</spirit:right>
          </spirit:vector>
          <spirit:wireTypeDefs>
            <spirit:wireTypeDef>
              <spirit:typeName>std_logic_vector</spirit:typeName>
              <spirit:viewNameRef>xilinx_elaborateports</spirit:viewNameRef>
            </spirit:wireTypeDef>
          </spirit:wireTypeDefs>
        </spirit:wire>
      </spirit:port>
      <spirit:port>
        <spirit:name>s_axi_ctrl_mgmt_awprot</spirit:name>
        <spirit:wire>
          <spirit:direction>in</spirit:direction>
          <spirit:vector>
            <spirit:left spirit:format="long">2</spirit:left>
            <spirit:right spirit:format="long">0</spirit:right>
          </spirit:vector>
          <spirit:wireTypeDefs>
            <spirit:wireTypeDef>
              <spirit:typeName>std_logic_vector</spirit:typeName>
              <spirit:viewNameRef>xilinx_elaborateports</spirit:viewNameRef>
            </spirit:wireTypeDef>
          </spirit:wireTypeDefs>
        </spirit:wire>
      </spirit:port>
      <spirit:port>
        <spirit:name>s_axi_ctrl_mgmt_awvalid</spirit:name>
        <spirit:wire>
          <spirit:direction>in</spirit:direction>
          <spirit:vector>
            <spirit:left spirit:format="long">0</spirit:left>
            <spirit:right spirit:format="long">0</spirit:right>
          </spirit:vector>
          <spirit:wireTypeDefs>
            <spirit:wireTypeDef>
              <spirit:typeName>std_logic_vector</spirit:typeName>
              <spirit:viewNameRef>xilinx_elaborateports</spirit:viewNameRef>
            </spirit:wireTypeDef>
          </spirit:wireTypeDefs>
        </spirit:wire>
      </spirit:port>
      <spirit:port>
        <spirit:name>s_axi_ctrl_mgmt_awready</spirit:name>
        <spirit:wire>
          <spirit:direction>out</spirit:direction>
          <spirit:vector>
            <spirit:left spirit:format="long">0</spirit:left>
            <spirit:right spirit:format="long">0</spirit:right>
          </spirit:vector>
          <spirit:wireTypeDefs>
            <spirit:wireTypeDef>
              <spirit:typeName>std_logic_vector</spirit:typeName>
              <spirit:viewNameRef>xilinx_elaborateports</spirit:viewNameRef>
            </spirit:wireTypeDef>
          </spirit:wireTypeDefs>
        </spirit:wire>
      </spirit:port>
      <spirit:port>
        <spirit:name>s_axi_ctrl_mgmt_wdata</spirit:name>
        <spirit:wire>
          <spirit:direction>in</spirit:direction>
          <spirit:vector>
            <spirit:left spirit:format="long">31</spirit:left>
            <spirit:right spirit:format="long">0</spirit:right>
          </spirit:vector>
          <spirit:wireTypeDefs>
            <spirit:wireTypeDef>
              <spirit:typeName>std_logic_vector</spirit:typeName>
              <spirit:viewNameRef>xilinx_elaborateports</spirit:viewNameRef>
            </spirit:wireTypeDef>
          </spirit:wireTypeDefs>
        </spirit:wire>
      </spirit:port>
      <spirit:port>
        <spirit:name>s_axi_ctrl_mgmt_wstrb</spirit:name>
        <spirit:wire>
          <spirit:direction>in</spirit:direction>
          <spirit:vector>
            <spirit:left spirit:format="long">3</spirit:left>
            <spirit:right spirit:format="long">0</spirit:right>
          </spirit:vector>
          <spirit:wireTypeDefs>
            <spirit:wireTypeDef>
              <spirit:typeName>std_logic_vector</spirit:typeName>
              <spirit:viewNameRef>xilinx_elaborateports</spirit:viewNameRef>
            </spirit:wireTypeDef>
          </spirit:wireTypeDefs>
        </spirit:wire>
      </spirit:port>
      <spirit:port>
        <spirit:name>s_axi_ctrl_mgmt_wvalid</spirit:name>
        <spirit:wire>
          <spirit:direction>in</spirit:direction>
          <spirit:vector>
            <spirit:left spirit:format="long">0</spirit:left>
            <spirit:right spirit:format="long">0</spirit:right>
          </spirit:vector>
          <spirit:wireTypeDefs>
            <spirit:wireTypeDef>
              <spirit:typeName>std_logic_vector</spirit:typeName>
              <spirit:viewNameRef>xilinx_elaborateports</spirit:viewNameRef>
            </spirit:wireTypeDef>
          </spirit:wireTypeDefs>
        </spirit:wire>
      </spirit:port>
      <spirit:port>
        <spirit:name>s_axi_ctrl_mgmt_wready</spirit:name>
        <spirit:wire>
          <spirit:direction>out</spirit:direction>
          <spirit:vector>
            <spirit:left spirit:format="long">0</spirit:left>
            <spirit:right spirit:format="long">0</spirit:right>
          </spirit:vector>
          <spirit:wireTypeDefs>
            <spirit:wireTypeDef>
              <spirit:typeName>std_logic_vector</spirit:typeName>
              <spirit:viewNameRef>xilinx_elaborateports</spirit:viewNameRef>
            </spirit:wireTypeDef>
          </spirit:wireTypeDefs>
        </spirit:wire>
      </spirit:port>
      <spirit:port>
        <spirit:name>s_axi_ctrl_mgmt_bresp</spirit:name>
        <spirit:wire>
          <spirit:direction>out</spirit:direction>
          <spirit:vector>
            <spirit:left spirit:format="long">1</spirit:left>
            <spirit:right spirit:format="long">0</spirit:right>
          </spirit:vector>
          <spirit:wireTypeDefs>
            <spirit:wireTypeDef>
              <spirit:typeName>std_logic_vector</spirit:typeName>
              <spirit:viewNameRef>xilinx_elaborateports</spirit:viewNameRef>
            </spirit:wireTypeDef>
          </spirit:wireTypeDefs>
        </spirit:wire>
      </spirit:port>
      <spirit:port>
        <spirit:name>s_axi_ctrl_mgmt_bvalid</spirit:name>
        <spirit:wire>
          <spirit:direction>out</spirit:direction>
          <spirit:vector>
            <spirit:left spirit:format="long">0</spirit:left>
            <spirit:right spirit:format="long">0</spirit:right>
          </spirit:vector>
          <spirit:wireTypeDefs>
            <spirit:wireTypeDef>
              <spirit:typeName>std_logic_vector</spirit:typeName>
              <spirit:viewNameRef>xilinx_elaborateports</spirit:viewNameRef>
            </spirit:wireTypeDef>
          </spirit:wireTypeDefs>
        </spirit:wire>
      </spirit:port>
      <spirit:port>
        <spirit:name>s_axi_ctrl_mgmt_bready</spirit:name>
        <spirit:wire>
          <spirit:direction>in</spirit:direction>
          <spirit:vector>
            <spirit:left spirit:format="long">0</spirit:left>
            <spirit:right spirit:format="long">0</spirit:right>
          </spirit:vector>
          <spirit:wireTypeDefs>
            <spirit:wireTypeDef>
              <spirit:typeName>std_logic_vector</spirit:typeName>
              <spirit:viewNameRef>xilinx_elaborateports</spirit:viewNameRef>
            </spirit:wireTypeDef>
          </spirit:wireTypeDefs>
        </spirit:wire>
      </spirit:port>
      <spirit:port>
        <spirit:name>s_axi_ctrl_mgmt_araddr</spirit:name>
        <spirit:wire>
          <spirit:direction>in</spirit:direction>
          <spirit:vector>
            <spirit:left spirit:format="long">17</spirit:left>
            <spirit:right spirit:format="long">0</spirit:right>
          </spirit:vector>
          <spirit:wireTypeDefs>
            <spirit:wireTypeDef>
              <spirit:typeName>std_logic_vector</spirit:typeName>
              <spirit:viewNameRef>xilinx_elaborateports</spirit:viewNameRef>
            </spirit:wireTypeDef>
          </spirit:wireTypeDefs>
        </spirit:wire>
      </spirit:port>
      <spirit:port>
        <spirit:name>s_axi_ctrl_mgmt_arprot</spirit:name>
        <spirit:wire>
          <spirit:direction>in</spirit:direction>
          <spirit:vector>
            <spirit:left spirit:format="long">2</spirit:left>
            <spirit:right spirit:format="long">0</spirit:right>
          </spirit:vector>
          <spirit:wireTypeDefs>
            <spirit:wireTypeDef>
              <spirit:typeName>std_logic_vector</spirit:typeName>
              <spirit:viewNameRef>xilinx_elaborateports</spirit:viewNameRef>
            </spirit:wireTypeDef>
          </spirit:wireTypeDefs>
        </spirit:wire>
      </spirit:port>
      <spirit:port>
        <spirit:name>s_axi_ctrl_mgmt_arvalid</spirit:name>
        <spirit:wire>
          <spirit:direction>in</spirit:direction>
          <spirit:vector>
            <spirit:left spirit:format="long">0</spirit:left>
            <spirit:right spirit:format="long">0</spirit:right>
          </spirit:vector>
          <spirit:wireTypeDefs>
            <spirit:wireTypeDef>
              <spirit:typeName>std_logic_vector</spirit:typeName>
              <spirit:viewNameRef>xilinx_elaborateports</spirit:viewNameRef>
            </spirit:wireTypeDef>
          </spirit:wireTypeDefs>
        </spirit:wire>
      </spirit:port>
      <spirit:port>
        <spirit:name>s_axi_ctrl_mgmt_arready</spirit:name>
        <spirit:wire>
          <spirit:direction>out</spirit:direction>
          <spirit:vector>
            <spirit:left spirit:format="long">0</spirit:left>
            <spirit:right spirit:format="long">0</spirit:right>
          </spirit:vector>
          <spirit:wireTypeDefs>
            <spirit:wireTypeDef>
              <spirit:typeName>std_logic_vector</spirit:typeName>
              <spirit:viewNameRef>xilinx_elaborateports</spirit:viewNameRef>
            </spirit:wireTypeDef>
          </spirit:wireTypeDefs>
        </spirit:wire>
      </spirit:port>
      <spirit:port>
        <spirit:name>s_axi_ctrl_mgmt_rdata</spirit:name>
        <spirit:wire>
          <spirit:direction>out</spirit:direction>
          <spirit:vector>
            <spirit:left spirit:format="long">31</spirit:left>
            <spirit:right spirit:format="long">0</spirit:right>
          </spirit:vector>
          <spirit:wireTypeDefs>
            <spirit:wireTypeDef>
              <spirit:typeName>std_logic_vector</spirit:typeName>
              <spirit:viewNameRef>xilinx_elaborateports</spirit:viewNameRef>
            </spirit:wireTypeDef>
          </spirit:wireTypeDefs>
        </spirit:wire>
      </spirit:port>
      <spirit:port>
        <spirit:name>s_axi_ctrl_mgmt_rresp</spirit:name>
        <spirit:wire>
          <spirit:direction>out</spirit:direction>
          <spirit:vector>
            <spirit:left spirit:format="long">1</spirit:left>
            <spirit:right spirit:format="long">0</spirit:right>
          </spirit:vector>
          <spirit:wireTypeDefs>
            <spirit:wireTypeDef>
              <spirit:typeName>std_logic_vector</spirit:typeName>
              <spirit:viewNameRef>xilinx_elaborateports</spirit:viewNameRef>
            </spirit:wireTypeDef>
          </spirit:wireTypeDefs>
        </spirit:wire>
      </spirit:port>
      <spirit:port>
        <spirit:name>s_axi_ctrl_mgmt_rvalid</spirit:name>
        <spirit:wire>
          <spirit:direction>out</spirit:direction>
          <spirit:vector>
            <spirit:left spirit:format="long">0</spirit:left>
            <spirit:right spirit:format="long">0</spirit:right>
          </spirit:vector>
          <spirit:wireTypeDefs>
            <spirit:wireTypeDef>
              <spirit:typeName>std_logic_vector</spirit:typeName>
              <spirit:viewNameRef>xilinx_elaborateports</spirit:viewNameRef>
            </spirit:wireTypeDef>
          </spirit:wireTypeDefs>
        </spirit:wire>
      </spirit:port>
      <spirit:port>
        <spirit:name>s_axi_ctrl_mgmt_rready</spirit:name>
        <spirit:wire>
          <spirit:direction>in</spirit:direction>
          <spirit:vector>
            <spirit:left spirit:format="long">0</spirit:left>
            <spirit:right spirit:format="long">0</spirit:right>
          </spirit:vector>
          <spirit:wireTypeDefs>
            <spirit:wireTypeDef>
              <spirit:typeName>std_logic_vector</spirit:typeName>
              <spirit:viewNameRef>xilinx_elaborateports</spirit:viewNameRef>
            </spirit:wireTypeDef>
          </spirit:wireTypeDefs>
        </spirit:wire>
      </spirit:port>
      <spirit:port>
        <spirit:name>satellite_gpio_tri_i</spirit:name>
        <spirit:wire>
          <spirit:direction>in</spirit:direction>
          <spirit:vector>
            <spirit:left spirit:format="long">3</spirit:left>
            <spirit:right spirit:format="long">0</spirit:right>
          </spirit:vector>
          <spirit:wireTypeDefs>
            <spirit:wireTypeDef>
              <spirit:typeName>std_logic_vector</spirit:typeName>
              <spirit:viewNameRef>xilinx_elaborateports</spirit:viewNameRef>
            </spirit:wireTypeDef>
          </spirit:wireTypeDefs>
          <spirit:driver>
            <spirit:defaultValue spirit:format="long">0</spirit:defaultValue>
          </spirit:driver>
        </spirit:wire>
      </spirit:port>
      <spirit:port>
        <spirit:name>satellite_gpio_tri_o</spirit:name>
        <spirit:wire>
          <spirit:direction>out</spirit:direction>
          <spirit:vector>
            <spirit:left spirit:format="long">3</spirit:left>
            <spirit:right spirit:format="long">0</spirit:right>
          </spirit:vector>
          <spirit:wireTypeDefs>
            <spirit:wireTypeDef>
              <spirit:typeName>std_logic_vector</spirit:typeName>
              <spirit:viewNameRef>xilinx_elaborateports</spirit:viewNameRef>
            </spirit:wireTypeDef>
          </spirit:wireTypeDefs>
        </spirit:wire>
      </spirit:port>
      <spirit:port>
        <spirit:name>satellite_gpio_tri_t</spirit:name>
        <spirit:wire>
          <spirit:direction>out</spirit:direction>
          <spirit:vector>
            <spirit:left spirit:format="long">3</spirit:left>
            <spirit:right spirit:format="long">0</spirit:right>
          </spirit:vector>
          <spirit:wireTypeDefs>
            <spirit:wireTypeDef>
              <spirit:typeName>std_logic_vector</spirit:typeName>
              <spirit:viewNameRef>xilinx_elaborateports</spirit:viewNameRef>
            </spirit:wireTypeDef>
          </spirit:wireTypeDefs>
        </spirit:wire>
      </spirit:port>
    </spirit:ports>
  </spirit:model>
  <spirit:choices>
    <spirit:choice>
      <spirit:name>choice_list_aa1f9024</spirit:name>
      <spirit:enumeration>4k</spirit:enumeration>
      <spirit:enumeration>8k</spirit:enumeration>
      <spirit:enumeration>16k</spirit:enumeration>
      <spirit:enumeration>32k</spirit:enumeration>
      <spirit:enumeration>64k</spirit:enumeration>
      <spirit:enumeration>128k</spirit:enumeration>
      <spirit:enumeration>256k</spirit:enumeration>
      <spirit:enumeration>512k</spirit:enumeration>
      <spirit:enumeration>1M</spirit:enumeration>
      <spirit:enumeration>2M</spirit:enumeration>
      <spirit:enumeration>4M</spirit:enumeration>
      <spirit:enumeration>8M</spirit:enumeration>
      <spirit:enumeration>16M</spirit:enumeration>
      <spirit:enumeration>32M</spirit:enumeration>
      <spirit:enumeration>64M</spirit:enumeration>
      <spirit:enumeration>128M</spirit:enumeration>
      <spirit:enumeration>256M</spirit:enumeration>
      <spirit:enumeration>512M</spirit:enumeration>
      <spirit:enumeration>1G</spirit:enumeration>
      <spirit:enumeration>2G</spirit:enumeration>
      <spirit:enumeration>4G</spirit:enumeration>
    </spirit:choice>
    <spirit:choice>
      <spirit:name>choice_list_e2e307cd</spirit:name>
      <spirit:enumeration>4k</spirit:enumeration>
      <spirit:enumeration>8k</spirit:enumeration>
      <spirit:enumeration>16k</spirit:enumeration>
      <spirit:enumeration>32k</spirit:enumeration>
      <spirit:enumeration>64k</spirit:enumeration>
      <spirit:enumeration>128k</spirit:enumeration>
      <spirit:enumeration>256k</spirit:enumeration>
    </spirit:choice>
  </spirit:choices>
  <spirit:fileSets>
    <spirit:fileSet>
      <spirit:name>xilinx_elaborateports_view_fileset</spirit:name>
      <spirit:file>
        <spirit:name>../../../bd_1/bd_deec.bd</spirit:name>
        <spirit:userFileType>block_diagram</spirit:userFileType>
      </spirit:file>
    </spirit:fileSet>
    <spirit:fileSet>
      <spirit:name>xilinx_elaboratebd_view_fileset</spirit:name>
      <spirit:file>
        <spirit:name>../../../bd_1/bd_deec.bd</spirit:name>
        <spirit:userFileType>block_diagram</spirit:userFileType>
      </spirit:file>
    </spirit:fileSet>
  </spirit:fileSets>
  <spirit:description>This is a horizontal subsystem which contains the MicroBlaze-based Card Management Controller</spirit:description>
  <spirit:parameters>
    <spirit:parameter>
      <spirit:name>Component_Name</spirit:name>
      <spirit:value spirit:resolve="user" spirit:id="PARAM_VALUE.Component_Name" spirit:order="2">bd_3d9a_shell_cmc_subsystem_0</spirit:value>
      <spirit:vendorExtensions>
        <xilinx:parameterInfo>
          <xilinx:enablement>
            <xilinx:isEnabled xilinx:resolve="dependent" xilinx:id="PARAM_ENABLEMENT.Component_Name">true</xilinx:isEnabled>
          </xilinx:enablement>
        </xilinx:parameterInfo>
      </spirit:vendorExtensions>
    </spirit:parameter>
    <spirit:parameter>
      <spirit:name>HAS_AXI_IIC</spirit:name>
      <spirit:displayName>Include AXI IIC Block</spirit:displayName>
      <spirit:value spirit:format="bool" spirit:resolve="user" spirit:id="PARAM_VALUE.HAS_AXI_IIC" spirit:order="3">false</spirit:value>
      <spirit:vendorExtensions>
        <xilinx:parameterInfo>
          <xilinx:enablement>
            <xilinx:isEnabled xilinx:resolve="dependent" xilinx:id="PARAM_ENABLEMENT.HAS_AXI_IIC">true</xilinx:isEnabled>
          </xilinx:enablement>
        </xilinx:parameterInfo>
      </spirit:vendorExtensions>
    </spirit:parameter>
    <spirit:parameter>
      <spirit:name>HAS_QSFP_GPIO</spirit:name>
      <spirit:displayName>Include QSFP GPIO</spirit:displayName>
      <spirit:value spirit:format="bool" spirit:resolve="user" spirit:id="PARAM_VALUE.HAS_QSFP_GPIO" spirit:order="4">true</spirit:value>
    </spirit:parameter>
    <spirit:parameter>
      <spirit:name>HAS_USB_UART</spirit:name>
      <spirit:displayName>Include UAB UART Block</spirit:displayName>
      <spirit:value spirit:format="bool" spirit:resolve="user" spirit:id="PARAM_VALUE.HAS_USB_UART" spirit:order="5">false</spirit:value>
      <spirit:vendorExtensions>
        <xilinx:parameterInfo>
          <xilinx:enablement>
            <xilinx:isEnabled xilinx:resolve="dependent" xilinx:id="PARAM_ENABLEMENT.HAS_USB_UART">true</xilinx:isEnabled>
          </xilinx:enablement>
        </xilinx:parameterInfo>
      </spirit:vendorExtensions>
    </spirit:parameter>
    <spirit:parameter>
      <spirit:name>NUM_SATELLITE_GPIO</spirit:name>
      <spirit:displayName>Select Number of Satellite GPIO</spirit:displayName>
      <spirit:value spirit:format="long" spirit:resolve="user" spirit:id="PARAM_VALUE.NUM_SATELLITE_GPIO" spirit:order="6" spirit:minimum="0" spirit:maximum="32" spirit:rangeType="long">4</spirit:value>
    </spirit:parameter>
    <spirit:parameter>
      <spirit:name>HAS_EXTERNAL_M_AXILITE</spirit:name>
      <spirit:displayName>Include external Master AXI-Lite interface</spirit:displayName>
      <spirit:value spirit:format="bool" spirit:resolve="user" spirit:id="PARAM_VALUE.HAS_EXTERNAL_M_AXILITE" spirit:order="7">false</spirit:value>
      <spirit:vendorExtensions>
        <xilinx:parameterInfo>
          <xilinx:enablement>
            <xilinx:isEnabled xilinx:resolve="dependent" xilinx:id="PARAM_ENABLEMENT.HAS_EXTERNAL_M_AXILITE">true</xilinx:isEnabled>
          </xilinx:enablement>
        </xilinx:parameterInfo>
      </spirit:vendorExtensions>
    </spirit:parameter>
    <spirit:parameter>
      <spirit:name>ENABLE_AXI_IC_PIPELINING</spirit:name>
      <spirit:displayName>Enable Pipeline registers in CMC local AXI Interconnect</spirit:displayName>
      <spirit:value spirit:format="bool" spirit:resolve="user" spirit:id="PARAM_VALUE.ENABLE_AXI_IC_PIPELINING" spirit:order="8">false</spirit:value>
      <spirit:vendorExtensions>
        <xilinx:parameterInfo>
          <xilinx:enablement>
            <xilinx:isEnabled xilinx:resolve="dependent" xilinx:id="PARAM_ENABLEMENT.ENABLE_AXI_IC_PIPELINING">true</xilinx:isEnabled>
          </xilinx:enablement>
        </xilinx:parameterInfo>
      </spirit:vendorExtensions>
    </spirit:parameter>
    <spirit:parameter>
      <spirit:name>NUM_HOST_INTERRUPTS</spirit:name>
      <spirit:displayName>Number of host interrupts generated by CMC Microblaze</spirit:displayName>
      <spirit:value spirit:format="long" spirit:resolve="user" spirit:id="PARAM_VALUE.NUM_HOST_INTERRUPTS" spirit:order="9" spirit:minimum="1" spirit:maximum="31" spirit:rangeType="long">31</spirit:value>
    </spirit:parameter>
    <spirit:parameter>
      <spirit:name>HOST_INTC_KIND_OF_INTR</spirit:name>
      <spirit:displayName>Interrupt type - Level (0) or Edge (1)</spirit:displayName>
      <spirit:value spirit:format="bitString" spirit:resolve="user" spirit:id="PARAM_VALUE.HOST_INTC_KIND_OF_INTR" spirit:order="10" spirit:bitStringLength="32">0xFFFFFFFF</spirit:value>
    </spirit:parameter>
    <spirit:parameter>
      <spirit:name>HOST_INTC_KIND_OF_EDGE</spirit:name>
      <spirit:displayName>Edge type - Falling (0) or Rising (1)</spirit:displayName>
      <spirit:value spirit:format="bitString" spirit:resolve="user" spirit:id="PARAM_VALUE.HOST_INTC_KIND_OF_EDGE" spirit:order="11" spirit:bitStringLength="32">0xFFFFFFFF</spirit:value>
    </spirit:parameter>
    <spirit:parameter>
      <spirit:name>HOST_INTC_KIND_OF_LVL</spirit:name>
      <spirit:displayName>Level type - Low (0) or High (1)</spirit:displayName>
      <spirit:value spirit:format="bitString" spirit:resolve="user" spirit:id="PARAM_VALUE.HOST_INTC_KIND_OF_LVL" spirit:order="12" spirit:bitStringLength="32">0xFFFFFFFF</spirit:value>
    </spirit:parameter>
    <spirit:parameter>
      <spirit:name>HOST_INTC_ASYNC_INTR</spirit:name>
      <spirit:displayName>Interrupt sync type - Sync (0) or Async (1)</spirit:displayName>
      <spirit:value spirit:format="bitString" spirit:resolve="user" spirit:id="PARAM_VALUE.HOST_INTC_ASYNC_INTR" spirit:order="13" spirit:bitStringLength="32">0x00000000</spirit:value>
    </spirit:parameter>
    <spirit:parameter>
      <spirit:name>CMC_INTC_KIND_OF_INTR</spirit:name>
      <spirit:displayName>Interrupt type - Level (0) or Edge (1)</spirit:displayName>
      <spirit:value spirit:format="bitString" spirit:resolve="user" spirit:id="PARAM_VALUE.CMC_INTC_KIND_OF_INTR" spirit:order="14" spirit:bitStringLength="32">0x00000240</spirit:value>
    </spirit:parameter>
    <spirit:parameter>
      <spirit:name>CMC_INTC_KIND_OF_EDGE</spirit:name>
      <spirit:displayName>Edge type - Falling (0) or Rising (1)</spirit:displayName>
      <spirit:value spirit:format="bitString" spirit:resolve="user" spirit:id="PARAM_VALUE.CMC_INTC_KIND_OF_EDGE" spirit:order="15" spirit:bitStringLength="32">0xFFFFFFFF</spirit:value>
    </spirit:parameter>
    <spirit:parameter>
      <spirit:name>CMC_INTC_KIND_OF_LVL</spirit:name>
      <spirit:displayName>Level type - Low (0) or High (1)</spirit:displayName>
      <spirit:value spirit:format="bitString" spirit:resolve="user" spirit:id="PARAM_VALUE.CMC_INTC_KIND_OF_LVL" spirit:order="16" spirit:bitStringLength="32">0xFFFFFFFF</spirit:value>
    </spirit:parameter>
    <spirit:parameter>
      <spirit:name>CMC_INTC_ASYNC_INTR</spirit:name>
      <spirit:displayName>Interrupt sync type - Sync (0) or Async (1)</spirit:displayName>
      <spirit:value spirit:format="bitString" spirit:resolve="user" spirit:id="PARAM_VALUE.CMC_INTC_ASYNC_INTR" spirit:order="17" spirit:bitStringLength="32">0x00008000</spirit:value>
    </spirit:parameter>
    <spirit:parameter>
      <spirit:name>OFFSET_AXI_BRAM_CTRL_FW_SEG</spirit:name>
      <spirit:displayName>AXI_BRAM_CTRL_FW offset</spirit:displayName>
      <spirit:value spirit:format="bitString" spirit:resolve="user" spirit:id="PARAM_VALUE.OFFSET_AXI_BRAM_CTRL_FW_SEG" spirit:order="18" spirit:bitStringLength="32">0x00000000</spirit:value>
    </spirit:parameter>
    <spirit:parameter>
      <spirit:name>RANGE_AXI_BRAM_CTRL_FW_SEG</spirit:name>
      <spirit:displayName>AXI_BRAM_CTRL_FW range</spirit:displayName>
      <spirit:value spirit:resolve="user" spirit:id="PARAM_VALUE.RANGE_AXI_BRAM_CTRL_FW_SEG" spirit:choiceRef="choice_list_e2e307cd" spirit:order="19">64k</spirit:value>
    </spirit:parameter>
    <spirit:parameter>
      <spirit:name>OFFSET_AXI_GPIO_MB_RESET_SEG</spirit:name>
      <spirit:displayName>AXI_GPIO_MB_RESET offset</spirit:displayName>
      <spirit:value spirit:format="bitString" spirit:resolve="user" spirit:id="PARAM_VALUE.OFFSET_AXI_GPIO_MB_RESET_SEG" spirit:order="20" spirit:bitStringLength="32">0x00020000</spirit:value>
    </spirit:parameter>
    <spirit:parameter>
      <spirit:name>RANGE_AXI_GPIO_MB_RESET_SEG</spirit:name>
      <spirit:displayName>AXI_GPIO_MB_RESET range</spirit:displayName>
      <spirit:value spirit:resolve="user" spirit:id="PARAM_VALUE.RANGE_AXI_GPIO_MB_RESET_SEG" spirit:choiceRef="choice_list_aa1f9024" spirit:order="21">4k</spirit:value>
    </spirit:parameter>
    <spirit:parameter>
      <spirit:name>OFFSET_AXI_GPIO_MUTEX_HOST_SEG</spirit:name>
      <spirit:displayName>AXI_GPIO_MUTEX_HOST offset</spirit:displayName>
      <spirit:value spirit:format="bitString" spirit:resolve="user" spirit:id="PARAM_VALUE.OFFSET_AXI_GPIO_MUTEX_HOST_SEG" spirit:order="22" spirit:bitStringLength="32">0x00021000</spirit:value>
    </spirit:parameter>
    <spirit:parameter>
      <spirit:name>RANGE_AXI_GPIO_MUTEX_HOST_SEG</spirit:name>
      <spirit:displayName>AXI_GPIO_MUTEX_HOST range</spirit:displayName>
      <spirit:value spirit:resolve="user" spirit:id="PARAM_VALUE.RANGE_AXI_GPIO_MUTEX_HOST_SEG" spirit:choiceRef="choice_list_aa1f9024" spirit:order="23">4k</spirit:value>
    </spirit:parameter>
    <spirit:parameter>
      <spirit:name>OFFSET_AXI_INTC_HOST_SEG</spirit:name>
      <spirit:displayName>AXI_INTC_HOST offset</spirit:displayName>
      <spirit:value spirit:format="bitString" spirit:resolve="user" spirit:id="PARAM_VALUE.OFFSET_AXI_INTC_HOST_SEG" spirit:order="24" spirit:bitStringLength="32">0x00022000</spirit:value>
    </spirit:parameter>
    <spirit:parameter>
      <spirit:name>RANGE_AXI_INTC_HOST_SEG</spirit:name>
      <spirit:displayName>AXI_INTC_HOST range</spirit:displayName>
      <spirit:value spirit:resolve="user" spirit:id="PARAM_VALUE.RANGE_AXI_INTC_HOST_SEG" spirit:choiceRef="choice_list_e2e307cd" spirit:order="25">4k</spirit:value>
    </spirit:parameter>
    <spirit:parameter>
      <spirit:name>OFFSET_AXI_BRAM_CTRL_REGMAP_HOST_SEG</spirit:name>
      <spirit:displayName>AXI_BRAM_CTRL_REGMAP_HOST offset</spirit:displayName>
      <spirit:value spirit:format="bitString" spirit:resolve="user" spirit:id="PARAM_VALUE.OFFSET_AXI_BRAM_CTRL_REGMAP_HOST_SEG" spirit:order="26" spirit:bitStringLength="32">0x00028000</spirit:value>
    </spirit:parameter>
    <spirit:parameter>
      <spirit:name>RANGE_AXI_BRAM_CTRL_REGMAP_HOST_SEG</spirit:name>
      <spirit:displayName>AXI_BRAM_CTRL_REGMAP_HOST range</spirit:displayName>
      <spirit:value spirit:resolve="user" spirit:id="PARAM_VALUE.RANGE_AXI_BRAM_CTRL_REGMAP_HOST_SEG" spirit:choiceRef="choice_list_e2e307cd" spirit:order="27">8k</spirit:value>
    </spirit:parameter>
    <spirit:parameter>
      <spirit:name>OFFSET_AXI_GPIO_SATELLITE_SEG</spirit:name>
      <spirit:displayName>AXI_GPIO_SATELLITE offset</spirit:displayName>
      <spirit:value spirit:format="bitString" spirit:resolve="user" spirit:id="PARAM_VALUE.OFFSET_AXI_GPIO_SATELLITE_SEG" spirit:order="28" spirit:bitStringLength="32">0x01F00000</spirit:value>
    </spirit:parameter>
    <spirit:parameter>
      <spirit:name>RANGE_AXI_GPIO_SATELLITE_SEG</spirit:name>
      <spirit:displayName>AXI_GPIO_SATELLITE range</spirit:displayName>
      <spirit:value spirit:resolve="user" spirit:id="PARAM_VALUE.RANGE_AXI_GPIO_SATELLITE_SEG" spirit:choiceRef="choice_list_aa1f9024" spirit:order="29">64k</spirit:value>
    </spirit:parameter>
    <spirit:parameter>
      <spirit:name>OFFSET_AXI_GPIO_QSFP_SEG</spirit:name>
      <spirit:displayName>AXI_GPIO_QSFP offset</spirit:displayName>
      <spirit:value spirit:format="bitString" spirit:resolve="user" spirit:id="PARAM_VALUE.OFFSET_AXI_GPIO_QSFP_SEG" spirit:order="30" spirit:bitStringLength="32">0x01F10000</spirit:value>
    </spirit:parameter>
    <spirit:parameter>
      <spirit:name>RANGE_AXI_GPIO_QSFP_SEG</spirit:name>
      <spirit:displayName>AXI_GPIO_QSFP range</spirit:displayName>
      <spirit:value spirit:resolve="user" spirit:id="PARAM_VALUE.RANGE_AXI_GPIO_QSFP_SEG" spirit:choiceRef="choice_list_aa1f9024" spirit:order="31">64k</spirit:value>
    </spirit:parameter>
    <spirit:parameter>
      <spirit:name>OFFSET_AXI_GPIO_HBM_SEG</spirit:name>
      <spirit:displayName>AXI_GPIO_HBM offset</spirit:displayName>
      <spirit:value spirit:format="bitString" spirit:resolve="user" spirit:id="PARAM_VALUE.OFFSET_AXI_GPIO_HBM_SEG" spirit:order="32" spirit:bitStringLength="32">0x01F20000</spirit:value>
    </spirit:parameter>
    <spirit:parameter>
      <spirit:name>RANGE_AXI_GPIO_HBM_SEG</spirit:name>
      <spirit:displayName>AXI_GPIO_HBM range</spirit:displayName>
      <spirit:value spirit:resolve="user" spirit:id="PARAM_VALUE.RANGE_AXI_GPIO_HBM_SEG" spirit:choiceRef="choice_list_aa1f9024" spirit:order="33">64k</spirit:value>
    </spirit:parameter>
    <spirit:parameter>
      <spirit:name>OFFSET_AXI_GPIO_MB_INT_SEG</spirit:name>
      <spirit:displayName>AXI_GPIO_MB_INT offset</spirit:displayName>
      <spirit:value spirit:format="bitString" spirit:resolve="user" spirit:id="PARAM_VALUE.OFFSET_AXI_GPIO_MB_INT_SEG" spirit:order="34" spirit:bitStringLength="32">0x01F30000</spirit:value>
    </spirit:parameter>
    <spirit:parameter>
      <spirit:name>RANGE_AXI_GPIO_MB_INT_SEG</spirit:name>
      <spirit:displayName>AXI_GPIO_MB_INT range</spirit:displayName>
      <spirit:value spirit:resolve="user" spirit:id="PARAM_VALUE.RANGE_AXI_GPIO_MB_INT_SEG" spirit:choiceRef="choice_list_aa1f9024" spirit:order="35">64k</spirit:value>
    </spirit:parameter>
    <spirit:parameter>
      <spirit:name>OFFSET_AXI_GPIO_WDT_SEG</spirit:name>
      <spirit:displayName>AXI_GPIO_WDT offset</spirit:displayName>
      <spirit:value spirit:format="bitString" spirit:resolve="user" spirit:id="PARAM_VALUE.OFFSET_AXI_GPIO_WDT_SEG" spirit:order="36" spirit:bitStringLength="32">0x01F40000</spirit:value>
    </spirit:parameter>
    <spirit:parameter>
      <spirit:name>RANGE_AXI_GPIO_WDT_SEG</spirit:name>
      <spirit:displayName>AXI_GPIO_WDT range</spirit:displayName>
      <spirit:value spirit:resolve="user" spirit:id="PARAM_VALUE.RANGE_AXI_GPIO_WDT_SEG" spirit:choiceRef="choice_list_aa1f9024" spirit:order="37">64k</spirit:value>
    </spirit:parameter>
    <spirit:parameter>
      <spirit:name>OFFSET_AXI_INTC_SEG</spirit:name>
      <spirit:displayName>AXI_INTC offset</spirit:displayName>
      <spirit:value spirit:format="bitString" spirit:resolve="user" spirit:id="PARAM_VALUE.OFFSET_AXI_INTC_SEG" spirit:order="38" spirit:bitStringLength="32">0x01F50000</spirit:value>
    </spirit:parameter>
    <spirit:parameter>
      <spirit:name>RANGE_AXI_INTC_SEG</spirit:name>
      <spirit:displayName>AXI_INTC range</spirit:displayName>
      <spirit:value spirit:resolve="user" spirit:id="PARAM_VALUE.RANGE_AXI_INTC_SEG" spirit:choiceRef="choice_list_aa1f9024" spirit:order="39">64k</spirit:value>
    </spirit:parameter>
    <spirit:parameter>
      <spirit:name>OFFSET_AXI_TIMEBASE_WDT_SEG</spirit:name>
      <spirit:displayName>AXI_TIMEBASE_WDT offset</spirit:displayName>
      <spirit:value spirit:format="bitString" spirit:resolve="user" spirit:id="PARAM_VALUE.OFFSET_AXI_TIMEBASE_WDT_SEG" spirit:order="40" spirit:bitStringLength="32">0x01F60000</spirit:value>
    </spirit:parameter>
    <spirit:parameter>
      <spirit:name>RANGE_AXI_TIMEBASE_WDT_SEG</spirit:name>
      <spirit:displayName>AXI_TIMEBASE_WDT range</spirit:displayName>
      <spirit:value spirit:resolve="user" spirit:id="PARAM_VALUE.RANGE_AXI_TIMEBASE_WDT_SEG" spirit:choiceRef="choice_list_aa1f9024" spirit:order="41">64k</spirit:value>
    </spirit:parameter>
    <spirit:parameter>
      <spirit:name>OFFSET_AXI_UART_SATELLITE_SEG</spirit:name>
      <spirit:displayName>AXI_UART_SATELLITE offset</spirit:displayName>
      <spirit:value spirit:format="bitString" spirit:resolve="user" spirit:id="PARAM_VALUE.OFFSET_AXI_UART_SATELLITE_SEG" spirit:order="42" spirit:bitStringLength="32">0x01F70000</spirit:value>
    </spirit:parameter>
    <spirit:parameter>
      <spirit:name>RANGE_AXI_UART_SATELLITE_SEG</spirit:name>
      <spirit:displayName>AXI_UART_SATELLITE range</spirit:displayName>
      <spirit:value spirit:resolve="user" spirit:id="PARAM_VALUE.RANGE_AXI_UART_SATELLITE_SEG" spirit:choiceRef="choice_list_aa1f9024" spirit:order="43">64k</spirit:value>
    </spirit:parameter>
    <spirit:parameter>
      <spirit:name>OFFSET_AXI_UART_USB_SEG</spirit:name>
      <spirit:displayName>AXI_UART_USB offset</spirit:displayName>
      <spirit:value spirit:format="bitString" spirit:resolve="user" spirit:id="PARAM_VALUE.OFFSET_AXI_UART_USB_SEG" spirit:order="44" spirit:bitStringLength="32">0x01F80000</spirit:value>
    </spirit:parameter>
    <spirit:parameter>
      <spirit:name>RANGE_AXI_UART_USB_SEG</spirit:name>
      <spirit:displayName>AXI_UART_USB range</spirit:displayName>
      <spirit:value spirit:resolve="user" spirit:id="PARAM_VALUE.RANGE_AXI_UART_USB_SEG" spirit:choiceRef="choice_list_aa1f9024" spirit:order="45">64k</spirit:value>
    </spirit:parameter>
    <spirit:parameter>
      <spirit:name>OFFSET_TIMEBASE_COUNTER_SEG</spirit:name>
      <spirit:displayName>TIMEBASE_COUNTER offset</spirit:displayName>
      <spirit:value spirit:format="bitString" spirit:resolve="user" spirit:id="PARAM_VALUE.OFFSET_TIMEBASE_COUNTER_SEG" spirit:order="46" spirit:bitStringLength="32">0x01F90000</spirit:value>
    </spirit:parameter>
    <spirit:parameter>
      <spirit:name>RANGE_TIMEBASE_COUNTER_SEG</spirit:name>
      <spirit:displayName>TIMEBASE_COUNTER range</spirit:displayName>
      <spirit:value spirit:resolve="user" spirit:id="PARAM_VALUE.RANGE_TIMEBASE_COUNTER_SEG" spirit:choiceRef="choice_list_aa1f9024" spirit:order="47">64k</spirit:value>
    </spirit:parameter>
    <spirit:parameter>
      <spirit:name>OFFSET_AXI_BRAM_CTRL_REGMAP_CMC_SEG</spirit:name>
      <spirit:displayName>AXI_BRAM_CTRL_REGMAP_CMC offset</spirit:displayName>
      <spirit:value spirit:format="bitString" spirit:resolve="user" spirit:id="PARAM_VALUE.OFFSET_AXI_BRAM_CTRL_REGMAP_CMC_SEG" spirit:order="48" spirit:bitStringLength="32">0x01FA0000</spirit:value>
    </spirit:parameter>
    <spirit:parameter>
      <spirit:name>RANGE_AXI_BRAM_CTRL_REGMAP_CMC_SEG</spirit:name>
      <spirit:displayName>AXI_BRAM_CTRL_REGMAP_CMC range</spirit:displayName>
      <spirit:value spirit:resolve="user" spirit:id="PARAM_VALUE.RANGE_AXI_BRAM_CTRL_REGMAP_CMC_SEG" spirit:choiceRef="choice_list_aa1f9024" spirit:order="49">8k</spirit:value>
    </spirit:parameter>
    <spirit:parameter>
      <spirit:name>OFFSET_AXI_GPIO_MUTEX_CMC_SEG</spirit:name>
      <spirit:displayName>AXI_GPIO_MUTEX_CMC offset</spirit:displayName>
      <spirit:value spirit:format="bitString" spirit:resolve="user" spirit:id="PARAM_VALUE.OFFSET_AXI_GPIO_MUTEX_CMC_SEG" spirit:order="50" spirit:bitStringLength="32">0x01FB0000</spirit:value>
    </spirit:parameter>
    <spirit:parameter>
      <spirit:name>RANGE_AXI_GPIO_MUTEX_CMC_SEG</spirit:name>
      <spirit:displayName>AXI_GPIO_MUTEX_CMC range</spirit:displayName>
      <spirit:value spirit:resolve="user" spirit:id="PARAM_VALUE.RANGE_AXI_GPIO_MUTEX_CMC_SEG" spirit:choiceRef="choice_list_aa1f9024" spirit:order="51">64k</spirit:value>
    </spirit:parameter>
    <spirit:parameter>
      <spirit:name>OFFSET_AXI_IIC_SEG</spirit:name>
      <spirit:displayName>AXI_IIC offset</spirit:displayName>
      <spirit:value spirit:format="bitString" spirit:resolve="user" spirit:id="PARAM_VALUE.OFFSET_AXI_IIC_SEG" spirit:order="52" spirit:bitStringLength="32">0x01FC0000</spirit:value>
    </spirit:parameter>
    <spirit:parameter>
      <spirit:name>RANGE_AXI_IIC_SEG</spirit:name>
      <spirit:displayName>AXI_IIC range</spirit:displayName>
      <spirit:value spirit:resolve="user" spirit:id="PARAM_VALUE.RANGE_AXI_IIC_SEG" spirit:choiceRef="choice_list_aa1f9024" spirit:order="53">64k</spirit:value>
    </spirit:parameter>
    <spirit:parameter>
      <spirit:name>MB_BASE_VECTORS</spirit:name>
      <spirit:displayName>Microblaze Base Vector Address</spirit:displayName>
      <spirit:value spirit:format="bitString" spirit:resolve="user" spirit:id="PARAM_VALUE.MB_BASE_VECTORS" spirit:order="54" spirit:bitStringLength="32">0xF0000000</spirit:value>
    </spirit:parameter>
  </spirit:parameters>
  <spirit:vendorExtensions>
    <xilinx:coreExtensions>
      <xilinx:displayName>Shell Card Management Controller Subsystem</xilinx:displayName>
      <xilinx:xpmLibraries>
        <xilinx:xpmLibrary>XPM_MEMORY</xilinx:xpmLibrary>
        <xilinx:xpmLibrary>XPM_CDC</xilinx:xpmLibrary>
      </xilinx:xpmLibraries>
      <xilinx:coreRevision>0</xilinx:coreRevision>
      <xilinx:requiresVIP>true</xilinx:requiresVIP>
      <xilinx:tags>
        <xilinx:tag xilinx:name="driver_mode">subcore</xilinx:tag>
      </xilinx:tags>
      <xilinx:configElementInfos>
        <xilinx:configElementInfo xilinx:referenceId="BUSIFPARAM_VALUE.CLK.ACLK_CTRL.ASSOCIATED_BUSIF" xilinx:valueSource="user" xilinx:valuePermission="bd"/>
        <xilinx:configElementInfo xilinx:referenceId="BUSIFPARAM_VALUE.CLK.ACLK_CTRL.ASSOCIATED_CLKEN" xilinx:valueSource="constant" xilinx:valuePermission="bd"/>
        <xilinx:configElementInfo xilinx:referenceId="BUSIFPARAM_VALUE.CLK.ACLK_CTRL.ASSOCIATED_RESET" xilinx:valueSource="user" xilinx:valuePermission="bd"/>
        <xilinx:configElementInfo xilinx:referenceId="BUSIFPARAM_VALUE.CLK.ACLK_CTRL.CLK_DOMAIN" xilinx:valuePermission="bd"/>
        <xilinx:configElementInfo xilinx:referenceId="BUSIFPARAM_VALUE.CLK.ACLK_CTRL.FREQ_HZ" xilinx:valueSource="propagated" xilinx:valuePermission="bd"/>
        <xilinx:configElementInfo xilinx:referenceId="BUSIFPARAM_VALUE.CLK.ACLK_CTRL.INSERT_VIP" xilinx:valueSource="user"/>
        <xilinx:configElementInfo xilinx:referenceId="BUSIFPARAM_VALUE.CLK.ACLK_CTRL.PHASE" xilinx:valuePermission="bd"/>
        <xilinx:configElementInfo xilinx:referenceId="BUSIFPARAM_VALUE.INTR.INTERRUPT_HOST.PortWidth" xilinx:valuePermission="bd"/>
        <xilinx:configElementInfo xilinx:referenceId="BUSIFPARAM_VALUE.INTR.INTERRUPT_HOST.SENSITIVITY" xilinx:valueSource="user" xilinx:valuePermission="bd"/>
        <xilinx:configElementInfo xilinx:referenceId="BUSIFPARAM_VALUE.RST.ARESETN_CTRL.INSERT_VIP" xilinx:valueSource="user"/>
        <xilinx:configElementInfo xilinx:referenceId="BUSIFPARAM_VALUE.RST.ARESETN_CTRL.POLARITY" xilinx:valueSource="constant" xilinx:valuePermission="bd"/>
        <xilinx:configElementInfo xilinx:referenceId="BUSIFPARAM_VALUE.RST.MDM_DEBUG_SYS_RST.INSERT_VIP" xilinx:valueSource="user"/>
        <xilinx:configElementInfo xilinx:referenceId="BUSIFPARAM_VALUE.RST.MDM_DEBUG_SYS_RST.POLARITY" xilinx:valueSource="user" xilinx:valuePermission="bd"/>
        <xilinx:configElementInfo xilinx:referenceId="BUSIFPARAM_VALUE.S_AXI_CTRL_MGMT.ADDR_WIDTH" xilinx:valueSource="user" xilinx:valuePermission="bd"/>
        <xilinx:configElementInfo xilinx:referenceId="BUSIFPARAM_VALUE.S_AXI_CTRL_MGMT.ARUSER_WIDTH" xilinx:valueSource="user" xilinx:valuePermission="bd"/>
        <xilinx:configElementInfo xilinx:referenceId="BUSIFPARAM_VALUE.S_AXI_CTRL_MGMT.AWUSER_WIDTH" xilinx:valueSource="user" xilinx:valuePermission="bd"/>
        <xilinx:configElementInfo xilinx:referenceId="BUSIFPARAM_VALUE.S_AXI_CTRL_MGMT.BUSER_WIDTH" xilinx:valueSource="user" xilinx:valuePermission="bd"/>
        <xilinx:configElementInfo xilinx:referenceId="BUSIFPARAM_VALUE.S_AXI_CTRL_MGMT.CLK_DOMAIN" xilinx:valuePermission="bd"/>
        <xilinx:configElementInfo xilinx:referenceId="BUSIFPARAM_VALUE.S_AXI_CTRL_MGMT.DATA_WIDTH" xilinx:valueSource="user" xilinx:valuePermission="bd"/>
        <xilinx:configElementInfo xilinx:referenceId="BUSIFPARAM_VALUE.S_AXI_CTRL_MGMT.FREQ_HZ" xilinx:valueSource="user" xilinx:valuePermission="bd"/>
        <xilinx:configElementInfo xilinx:referenceId="BUSIFPARAM_VALUE.S_AXI_CTRL_MGMT.HAS_BRESP" xilinx:valueSource="user" xilinx:valuePermission="bd"/>
        <xilinx:configElementInfo xilinx:referenceId="BUSIFPARAM_VALUE.S_AXI_CTRL_MGMT.HAS_BURST" xilinx:valueSource="user" xilinx:valuePermission="bd"/>
        <xilinx:configElementInfo xilinx:referenceId="BUSIFPARAM_VALUE.S_AXI_CTRL_MGMT.HAS_CACHE" xilinx:valueSource="user" xilinx:valuePermission="bd"/>
        <xilinx:configElementInfo xilinx:referenceId="BUSIFPARAM_VALUE.S_AXI_CTRL_MGMT.HAS_LOCK" xilinx:valueSource="user" xilinx:valuePermission="bd"/>
        <xilinx:configElementInfo xilinx:referenceId="BUSIFPARAM_VALUE.S_AXI_CTRL_MGMT.HAS_PROT" xilinx:valueSource="user" xilinx:valuePermission="bd"/>
        <xilinx:configElementInfo xilinx:referenceId="BUSIFPARAM_VALUE.S_AXI_CTRL_MGMT.HAS_QOS" xilinx:valueSource="user" xilinx:valuePermission="bd"/>
        <xilinx:configElementInfo xilinx:referenceId="BUSIFPARAM_VALUE.S_AXI_CTRL_MGMT.HAS_REGION" xilinx:valueSource="user" xilinx:valuePermission="bd"/>
        <xilinx:configElementInfo xilinx:referenceId="BUSIFPARAM_VALUE.S_AXI_CTRL_MGMT.HAS_RRESP" xilinx:valueSource="user" xilinx:valuePermission="bd"/>
        <xilinx:configElementInfo xilinx:referenceId="BUSIFPARAM_VALUE.S_AXI_CTRL_MGMT.HAS_WSTRB" xilinx:valueSource="user" xilinx:valuePermission="bd"/>
        <xilinx:configElementInfo xilinx:referenceId="BUSIFPARAM_VALUE.S_AXI_CTRL_MGMT.ID_WIDTH" xilinx:valuePermission="bd"/>
        <xilinx:configElementInfo xilinx:referenceId="BUSIFPARAM_VALUE.S_AXI_CTRL_MGMT.INSERT_VIP" xilinx:valueSource="user"/>
        <xilinx:configElementInfo xilinx:referenceId="BUSIFPARAM_VALUE.S_AXI_CTRL_MGMT.MAX_BURST_LENGTH" xilinx:valueSource="user" xilinx:valuePermission="bd"/>
        <xilinx:configElementInfo xilinx:referenceId="BUSIFPARAM_VALUE.S_AXI_CTRL_MGMT.NUM_READ_OUTSTANDING" xilinx:valueSource="user" xilinx:valuePermission="bd"/>
        <xilinx:configElementInfo xilinx:referenceId="BUSIFPARAM_VALUE.S_AXI_CTRL_MGMT.NUM_READ_THREADS" xilinx:valueSource="user" xilinx:valuePermission="bd"/>
        <xilinx:configElementInfo xilinx:referenceId="BUSIFPARAM_VALUE.S_AXI_CTRL_MGMT.NUM_WRITE_OUTSTANDING" xilinx:valueSource="user" xilinx:valuePermission="bd"/>
        <xilinx:configElementInfo xilinx:referenceId="BUSIFPARAM_VALUE.S_AXI_CTRL_MGMT.NUM_WRITE_THREADS" xilinx:valueSource="user" xilinx:valuePermission="bd"/>
        <xilinx:configElementInfo xilinx:referenceId="BUSIFPARAM_VALUE.S_AXI_CTRL_MGMT.PHASE" xilinx:valuePermission="bd"/>
        <xilinx:configElementInfo xilinx:referenceId="BUSIFPARAM_VALUE.S_AXI_CTRL_MGMT.PROTOCOL" xilinx:valueSource="user" xilinx:valuePermission="bd"/>
        <xilinx:configElementInfo xilinx:referenceId="BUSIFPARAM_VALUE.S_AXI_CTRL_MGMT.READ_WRITE_MODE" xilinx:valueSource="user" xilinx:valuePermission="bd"/>
        <xilinx:configElementInfo xilinx:referenceId="BUSIFPARAM_VALUE.S_AXI_CTRL_MGMT.RUSER_BITS_PER_BYTE" xilinx:valueSource="user" xilinx:valuePermission="bd"/>
        <xilinx:configElementInfo xilinx:referenceId="BUSIFPARAM_VALUE.S_AXI_CTRL_MGMT.RUSER_WIDTH" xilinx:valueSource="user" xilinx:valuePermission="bd"/>
        <xilinx:configElementInfo xilinx:referenceId="BUSIFPARAM_VALUE.S_AXI_CTRL_MGMT.SUPPORTS_NARROW_BURST" xilinx:valueSource="user" xilinx:valuePermission="bd"/>
        <xilinx:configElementInfo xilinx:referenceId="BUSIFPARAM_VALUE.S_AXI_CTRL_MGMT.WUSER_BITS_PER_BYTE" xilinx:valueSource="user" xilinx:valuePermission="bd"/>
        <xilinx:configElementInfo xilinx:referenceId="BUSIFPARAM_VALUE.S_AXI_CTRL_MGMT.WUSER_WIDTH" xilinx:valueSource="user" xilinx:valuePermission="bd"/>
        <xilinx:configElementInfo xilinx:referenceId="PARAM_VALUE.ENABLE_AXI_IC_PIPELINING" xilinx:valueSource="user"/>
        <xilinx:configElementInfo xilinx:referenceId="PARAM_VALUE.HAS_EXTERNAL_M_AXILITE" xilinx:valueSource="user"/>
        <xilinx:configElementInfo xilinx:referenceId="PARAM_VALUE.HAS_USB_UART" xilinx:valueSource="user"/>
        <xilinx:configElementInfo xilinx:referenceId="PARAM_VALUE.NUM_SATELLITE_GPIO" xilinx:valueSource="user"/>
      </xilinx:configElementInfos>
    </xilinx:coreExtensions>
    <xilinx:packagingInfo>
      <xilinx:xilinxVersion>2019.2</xilinx:xilinxVersion>
      <xilinx:checksum xilinx:scope="fileGroups" xilinx:value="5eaf3abb"/>
      <xilinx:checksum xilinx:scope="parameters" xilinx:value="d9b54fdf"/>
    </xilinx:packagingInfo>
  </spirit:vendorExtensions>
</spirit:component>
